Workbook

Sheet 商圈对比
A2: 八个商圈小户型10个月成本调整后回报率
A3: 仅精装/简装出售、整租；25–60㎡；先逐套计算，再对有效出售房源取中位数
A6: 商圈 | B6: 符合条件出售数 | C6: 匹配出售数 | D6: 匹配覆盖率 | E6: 出租房源数 | F6: 税费调整后回报率 | G6: 原10个月毛回报率
A7: 川音 | B7: 28 | C7: 17 | D7: =C7/B7 -> 0.60714286 | E7: 50 | F7: =(G7-税费参数!$B$12*SUM(税费参数!$B$9:税费参数!$B$10)/税费参数!$B$11)/(1+SUM(税费参数!$B$6:税费参数!$B$8)) -> 0.032774127 | G7: 0.035714286
A8: 棕北 | B8: 33 | C8: 29 | D8: =C8/B8 -> 0.87878788 | E8: 54 | F8: =(G8-税费参数!$B$12*SUM(税费参数!$B$9:税费参数!$B$10)/税费参数!$B$11)/(1+SUM(税费参数!$B$6:税费参数!$B$8)) -> 0.031436642 | G8: 0.034333333
A9: 西南财大 | B9: 36 | C9: 22 | D9: =C9/B9 -> 0.61111111 | E9: 85 | F9: =(G9-税费参数!$B$12*SUM(税费参数!$B$9:税费参数!$B$10)/税费参数!$B$11)/(1+SUM(税费参数!$B$6:税费参数!$B$8)) -> 0.030382841 | G9: 0.033245283
A10: 川大 | B10: 40 | C10: 34 | D10: =C10/B10 -> 0.85 | E10: 71 | F10: =(G10-税费参数!$B$12*SUM(税费参数!$B$9:税费参数!$B$10)/税费参数!$B$11)/(1+SUM(税费参数!$B$6:税费参数!$B$8)) -> 0.028208232 | G10: 0.031
A11: 华西 | B11: 28 | C11: 23 | D11: =C11/B11 -> 0.82142857 | E11: 73 | F11: =(G11-税费参数!$B$12*SUM(税费参数!$B$9:税费参数!$B$10)/税费参数!$B$11)/(1+SUM(税费参数!$B$6:税费参数!$B$8)) -> 0.028139052 | G11: 0.030928571
A12: 玉林 | B12: 11 | C12: 8 | D12: =C12/B12 -> 0.72727273 | E12: 29 | F12: =(G12-税费参数!$B$12*SUM(税费参数!$B$9:税费参数!$B$10)/税费参数!$B$11)/(1+SUM(税费参数!$B$6:税费参数!$B$8)) -> 0.024277974 | G12: 0.026942008
A13: 合江亭 | B13: 166 | C13: 124 | D13: =C13/B13 -> 0.74698795 | E13: 129 | F13: =(G13-税费参数!$B$12*SUM(税费参数!$B$9:税费参数!$B$10)/税费参数!$B$11)/(1+SUM(税费参数!$B$6:税费参数!$B$8)) -> 0.020981077 | G13: 0.023537962
A14: 盐市口 | B14: 197 | C14: 157 | D14: =C14/B14 -> 0.79695431 | E14: 201 | F14: =(G14-税费参数!$B$12*SUM(税费参数!$B$9:税费参数!$B$10)/税费参数!$B$11)/(1+SUM(税费参数!$B$6:税费参数!$B$8)) -> 0.015699861 | G14: 0.018085106
A16: 无可比出租房源的出售房源保留在“出售逐套”，回报率为空，不作为0%参与中位数。
A17: 每个出售房源的回报率＝该房源所有合格出租配对的回报率中位数；再汇总到户型、小区、商圈。
A18: 回报率已计买入3.25%及卖出2.25%/120个月摊销，可在“税费参数”调整；未扣物业费、修缮及出租税费。

Sheet 税费参数
A2: 投资回报率—可调整税费参数
A5: 项目 | B5: 参数值
A6: 买入契税 | B6: 0.01
A7: 买入个税 | B7: 0.01
A8: 买入中介费 | B8: 0.0125
A9: 卖出个税 | B9: 0.01
A10: 卖出中介费 | B10: 0.0125
A11: 卖出成本摊销月数 | B11: 120
A12: 年计租月数 | B12: 10
A14: 计算口径：年计租月数 ×（月租金 − 房价×(卖出个税＋卖出中介费)÷摊销月数）÷（房价×(1＋买入契税＋买入个税＋买入中介费)）
A15: 卖出税费按房价计提；每月扣除1/120，不是一次性扣除。所有价格均为挂牌价。
A16: 未计物业费、维修、额外税费、房屋空置损失及价格涨跌；10个月已体现简化空置假设。

Sheet 小区汇总
A2: 104个小区的成本调整后回报率
A3: 匹配不到租金的小区仍予保留；小区回报率为其有效出售房源回报率的中位数
A6: 商圈 | B6: 小区 | C6: 精简装出售数 | D6: 有租金匹配数 | E6: 覆盖率 | F6: 税费调整后回报率 | G6: 原毛回报率
A7: 华西 | B7: 艺墅花乡 | C7: 9 | D7: 7 | E7: =D7/C7 -> 0.77777778 | F7: =(G7-税费参数!$B$12*SUM(税费参数!$B$9:税费参数!$B$10)/税费参数!$B$11)/(1+SUM(税费参数!$B$6:税费参数!$B$8)) -> 0.033251232 | G7: 0.036206897
A8: 华西 | B8: 金茂礼都 | C8: 6 | D8: 6 | E8: =D8/C8 -> 1 | F8: =(G8-税费参数!$B$12*SUM(税费参数!$B$9:税费参数!$B$10)/税费参数!$B$11)/(1+SUM(税费参数!$B$6:税费参数!$B$8)) -> 0.030071635 | G8: 0.032923963
A9: 华西 | B9: 天乐嘉苑 | C9: 1 | D9: 1 | E9: =D9/C9 -> 1 | F9: =(G9-税费参数!$B$12*SUM(税费参数!$B$9:税费参数!$B$10)/税费参数!$B$11)/(1+SUM(税费参数!$B$6:税费参数!$B$8)) -> 0.029881136 | G9: 0.032727273
A10: 华西 | B10: 天竺丽苑 | C10: 2 | D10: 1 | E10: =D10/C10 -> 0.5 | F10: =(G10-税费参数!$B$12*SUM(税费参数!$B$9:税费参数!$B$10)/税费参数!$B$11)/(1+SUM(税费参数!$B$6:税费参数!$B$8)) -> 0.026594027 | G10: 0.029333333
A11: 华西 | B11: 黉门公馆 | C11: 3 | D11: 2 | E11: =D11/C11 -> 0.66666667 | F11: =(G11-税费参数!$B$12*SUM(税费参数!$B$9:税费参数!$B$10)/税费参数!$B$11)/(1+SUM(税费参数!$B$6:税费参数!$B$8)) -> 0.02610878 | G11: 0.028832315
A12: 华西 | B12: 凯蒂阳光 | C12: 2 | D12: 2 | E12: =D12/C12 -> 1 | F12: =(G12-税费参数!$B$12*SUM(税费参数!$B$9:税费参数!$B$10)/税费参数!$B$11)/(1+SUM(税费参数!$B$6:税费参数!$B$8)) -> 0.02573794 | G12: 0.028449423
A13: 华西 | B13: 城南世家 | C13: 1 | D13: 1 | E13: =D13/C13 -> 1 | F13: =(G13-税费参数!$B$12*SUM(税费参数!$B$9:税费参数!$B$10)/税费参数!$B$11)/(1+SUM(税费参数!$B$6:税费参数!$B$8)) -> 0.025453114 | G13: 0.02815534
A14: 华西 | B14: 傲仕门 | C14: 2 | D14: 2 | E14: =D14/C14 -> 1 | F14: =(G14-税费参数!$B$12*SUM(税费参数!$B$9:税费参数!$B$10)/税费参数!$B$11)/(1+SUM(税费参数!$B$6:税费参数!$B$8)) -> 0.023671467 | G14: 0.026315789
A15: 华西 | B15: 米兰风度花园 | C15: 5 | D15: 4 | E15: =D15/C15 -> 0.8 | F15: =(G15-税费参数!$B$12*SUM(税费参数!$B$9:税费参数!$B$10)/税费参数!$B$11)/(1+SUM(税费参数!$B$6:税费参数!$B$8)) -> 0.021503517 | G15: 0.024077381
A16: 华西 | B16: 通祠路14号 | C16: 1 | D16: 1 | E16: =D16/C16 -> 1 | F16: =(G16-税费参数!$B$12*SUM(税费参数!$B$9:税费参数!$B$10)/税费参数!$B$11)/(1+SUM(税费参数!$B$6:税费参数!$B$8)) -> 0.020914661 | G16: 0.023469388
A17: 华西 | B17: 丽景天成 | C17: 9 | D17: 4 | E17: =D17/C17 -> 0.44444444 | F17: =(G17-税费参数!$B$12*SUM(税费参数!$B$9:税费参数!$B$10)/税费参数!$B$11)/(1+SUM(税费参数!$B$6:税费参数!$B$8)) -> 0.019982595 | G17: 0.022507029
A18: 华西 | B18: 人民南路三段16号 | C18: 1 | D18: 0 | E18: =D18/C18 -> 0
A19: 华西 | B19: 铜锣湾 | C19: 1 | D19: 0 | E19: =D19/C19 -> 0
A20: 华西 | B20: 锦和名邸 | C20: 1 | D20: 0 | E20: =D20/C20 -> 0
A21: 合江亭 | B21: 龙瑞苑 | C21: 1 | D21: 1 | E21: =D21/C21 -> 1 | F21: =(G21-税费参数!$B$12*SUM(税费参数!$B$9:税费参数!$B$10)/税费参数!$B$11)/(1+SUM(税费参数!$B$6:税费参数!$B$8)) -> 0.027372384 | G21: 0.030136986
A22: 合江亭 | B22: 流星花园 | C22: 26 | D22: 25 | E22: =D22/C22 -> 0.96153846 | F22: =(G22-税费参数!$B$12*SUM(税费参数!$B$9:税费参数!$B$10)/税费参数!$B$11)/(1+SUM(税费参数!$B$6:税费参数!$B$8)) -> 0.025224662 | G22: 0.027919463
A23: 合江亭 | B23: SOHO我的寓所 | C23: 6 | D23: 4 | E23: =D23/C23 -> 0.66666667 | F23: =(G23-税费参数!$B$12*SUM(税费参数!$B$9:税费参数!$B$10)/税费参数!$B$11)/(1+SUM(税费参数!$B$6:税费参数!$B$8)) -> 0.024523499 | G23: 0.027195513
A24: 合江亭 | B24: 总府花园 | C24: 4 | D24: 3 | E24: =D24/C24 -> 0.75 | F24: =(G24-税费参数!$B$12*SUM(税费参数!$B$9:税费参数!$B$10)/税费参数!$B$11)/(1+SUM(税费参数!$B$6:税费参数!$B$8)) -> 0.022871861 | G24: 0.025490196
A25: 合江亭 | B25: 喜年广场 | C25: 27 | D25: 27 | E25: =D25/C25 -> 1 | F25: =(G25-税费参数!$B$12*SUM(税费参数!$B$9:税费参数!$B$10)/税费参数!$B$11)/(1+SUM(税费参数!$B$6:税费参数!$B$8)) -> 0.022166494 | G25: 0.024761905
A26: 合江亭 | B26: 蓉上坊一期 | C26: 13 | D26: 12 | E26: =D26/C26 -> 0.92307692 | F26: =(G26-税费参数!$B$12*SUM(税费参数!$B$9:税费参数!$B$10)/税费参数!$B$11)/(1+SUM(税费参数!$B$6:税费参数!$B$8)) -> 0.022109046 | G26: 0.02470259
A27: 合江亭 | B27: 上东吉座 | C27: 2 | D27: 1 | E27: =D27/C27 -> 0.5 | F27: =(G27-税费参数!$B$12*SUM(税费参数!$B$9:税费参数!$B$10)/税费参数!$B$11)/(1+SUM(税费参数!$B$6:税费参数!$B$8)) -> 0.02039785 | G27: 0.02293578
A28: 合江亭 | B28: 银唐国际 | C28: 1 | D28: 1 | E28: =D28/C28 -> 1 | F28: =(G28-税费参数!$B$12*SUM(税费参数!$B$9:税费参数!$B$10)/税费参数!$B$11)/(1+SUM(税费参数!$B$6:税费参数!$B$8)) -> 0.020158911 | G28: 0.022689076
A29: 合江亭 | B29: 锦上花 | C29: 17 | D29: 13 | E29: =D29/C29 -> 0.76470588 | F29: =(G29-税费参数!$B$12*SUM(税费参数!$B$9:税费参数!$B$10)/税费参数!$B$11)/(1+SUM(税费参数!$B$6:税费参数!$B$8)) -> 0.019765238 | G29: 0.022282609
A30: 合江亭 | B30: 光辉岁月 | C30: 4 | D30: 3 | E30: =D30/C30 -> 0.75 | F30: =(G30-税费参数!$B$12*SUM(税费参数!$B$9:税费参数!$B$10)/税费参数!$B$11)/(1+SUM(税费参数!$B$6:税费参数!$B$8)) -> 0.019535549 | G30: 0.022045455
A31: 合江亭 | B31: 星城银座 | C31: 17 | D31: 14 | E31: =D31/C31 -> 0.82352941 | F31: =(G31-税费参数!$B$12*SUM(税费参数!$B$9:税费参数!$B$10)/税费参数!$B$11)/(1+SUM(税费参数!$B$6:税费参数!$B$8)) -> 0.018794096 | G31: 0.021279904
A32: 合江亭 | B32: 蓝光郁金香花园广场 | C32: 10 | D32: 8 | E32: =D32/C32 -> 0.8 | F32: =(G32-税费参数!$B$12*SUM(税费参数!$B$9:税费参数!$B$10)/税费参数!$B$11)/(1+SUM(税费参数!$B$6:税费参数!$B$8)) -> 0.018681112 | G32: 0.021163249
... A35: 合江亭 | B35: 国际商务大厦 | C35: 7 | D35: 5 | E35: =D35/C35 -> 0.71428571 | F35: =(G35-税费参数!$B$12*SUM(税费参数!$B$9:税费参数!$B$10)/税费参数!$B$11)/(1+SUM(税费参数!$B$6:税费参数!$B$8)) -> 0.016990291 | G35: 0.019417476
A36: 合江亭 | B36: 三圣街21号 | C36: 1 | D36: 0 | E36: =D36/C36 -> 0
A37: 合江亭 | B37: 水岸银座 | C37: 1 | D37: 0 | E37: =D37/C37 -> 0
A38: 合江亭 | B38: 蓝光时代华章 | C38: 24 | D38: 0 | E38: =D38/C38 -> 0
A39: 川大 | B39: 好望角 | C39: 5 | D39: 5 | E39: =D39/C39 -> 1 | F39: =(G39-税费参数!$B$12*SUM(税费参数!$B$9:税费参数!$B$10)/税费参数!$B$11)/(1+SUM(税费参数!$B$6:税费参数!$B$8)) -> 0.039346247 | G39: 0.0425
A40: 川大 | B40: 蓝色加勒比广场 | C40: 1 | D40: 1 | E40: =D40/C40 -> 1 | F40: =(G40-税费参数!$B$12*SUM(税费参数!$B$9:税费参数!$B$10)/税费参数!$B$11)/(1+SUM(税费参数!$B$6:税费参数!$B$8)) -> 0.031544256 | G40: 0.034444444
A41: 川大 | B41: 樱花假日 | C41: 19 | D41: 16 | E41: =D41/C41 -> 0.84210526 | F41: =(G41-税费参数!$B$12*SUM(税费参数!$B$9:税费参数!$B$10)/税费参数!$B$11)/(1+SUM(税费参数!$B$6:税费参数!$B$8)) -> 0.029596494 | G41: 0.03243338
A42: 川大 | B42: 中海格林威治城小户 | C42: 3 | D42: 3 | E42: =D42/C42 -> 1 | F42: =(G42-税费参数!$B$12*SUM(税费参数!$B$9:税费参数!$B$10)/税费参数!$B$11)/(1+SUM(税费参数!$B$6:税费参数!$B$8)) -> 0.028833481 | G42: 0.03164557
A43: 川大 | B43: 棕榈花园 | C43: 3 | D43: 2 | E43: =D43/C43 -> 0.66666667 | F43: =(G43-税费参数!$B$12*SUM(税费参数!$B$9:税费参数!$B$10)/税费参数!$B$11)/(1+SUM(税费参数!$B$6:税费参数!$B$8)) -> 0.028357236 | G43: 0.031153846
A44: 川大 | B44: 和信派都 | C44: 12 | D44: 12 | E44: =D44/C44 -> 1 | F44: =(G44-税费参数!$B$12*SUM(税费参数!$B$9:税费参数!$B$10)/税费参数!$B$11)/(1+SUM(税费参数!$B$6:税费参数!$B$8)) -> 0.024624267 | G44: 0.027299556
A45: 川大 | B45: 纯真年代 | C45: 6 | D45: 5 | E45: =D45/C45 -> 0.83333333 | F45: =(G45-税费参数!$B$12*SUM(税费参数!$B$9:税费参数!$B$10)/税费参数!$B$11)/(1+SUM(税费参数!$B$6:税费参数!$B$8)) -> 0.022719935 | G45: 0.025333333
A46: 川大 | B46: 新时空公寓 | C46: 3 | D46: 2 | E46: =D46/C46 -> 0.66666667 | F46: =(G46-税费参数!$B$12*SUM(税费参数!$B$9:税费参数!$B$10)/税费参数!$B$11)/(1+SUM(税费参数!$B$6:税费参数!$B$8)) -> 0.021130433 | G46: 0.023692173
A47: 川大 | B47: 海德花苑 | C47: 2 | D47: 1 | E47: =D47/C47 -> 0.5 | F47: =(G47-税费参数!$B$12*SUM(税费参数!$B$9:税费参数!$B$10)/税费参数!$B$11)/(1+SUM(税费参数!$B$6:税费参数!$B$8)) -> 0.014326069 | G47: 0.016666667
A48: 川大 | B48: 青年家园 | C48: 1 | D48: 0 | E48: =D48/C48 -> 0
A49: 川音 | B49: 锦宏骏苑南区 | C49: 1 | D49: 1 | E49: =D49/C49 -> 1 | F49: =(G49-税费参数!$B$12*SUM(税费参数!$B$9:税费参数!$B$10)/税费参数!$B$11)/(1+SUM(税费参数!$B$6:税费参数!$B$8)) -> 0.038064378 | G49: 0.041176471
A50: 川音 | B50: 凯悦新城 | C50: 15 | D50: 12 | E50: =D50/C50 -> 0.8 | F50: =(G50-税费参数!$B$12*SUM(税费参数!$B$9:税费参数!$B$10)/税费参数!$B$11)/(1+SUM(税费参数!$B$6:税费参数!$B$8)) -> 0.032823683 | G50: 0.035765452
A51: 川音 | B51: 时代100 | C51: 6 | D51: 1 | E51: =D51/C51 -> 0.16666667 | F51: =(G51-税费参数!$B$12*SUM(税费参数!$B$9:税费参数!$B$10)/税费参数!$B$11)/(1+SUM(税费参数!$B$6:税费参数!$B$8)) -> 0.025302663 | G51: 0.028
A52: 川音 | B52: 林荫嘉园 | C52: 10 | D52: 10 | E52: =D52/C52 -> 1 | F52: =(G52-税费参数!$B$12*SUM(税费参数!$B$9:税费参数!$B$10)/税费参数!$B$11)/(1+SUM(税费参数!$B$6:税费参数!$B$8)) -> 0.025231125 | G52: 0.027926136
A53: 川音 | B53: 临江路7号 | C53: 6 | D53: 2 | E53: =D53/C53 -> 0.33333333 | F53: =(G53-税费参数!$B$12*SUM(税费参数!$B$9:税费参数!$B$10)/税费参数!$B$11)/(1+SUM(税费参数!$B$6:税费参数!$B$8)) -> 0.025210061 | G53: 0.027904388
A54: 川音 | B54: 正黄上岭 | C54: 5 | D54: 4 | E54: =D54/C54 -> 0.8 | F54: =(G54-税费参数!$B$12*SUM(税费参数!$B$9:税费参数!$B$10)/税费参数!$B$11)/(1+SUM(税费参数!$B$6:税费参数!$B$8)) -> 0.024201267 | G54: 0.026862808
A55: 川音 | B55: 凯莱国际寓所 | C55: 4 | D55: 4 | E55: =D55/C55 -> 1 | F55: =(G55-税费参数!$B$12*SUM(税费参数!$B$9:税费参数!$B$10)/税费参数!$B$11)/(1+SUM(税费参数!$B$6:税费参数!$B$8)) -> 0.023560652 | G55: 0.026201373
A56: 川音 | B56: 摩卡筑 | C56: 8 | D56: 4 | E56: =D56/C56 -> 0.5 | F56: =(G56-税费参数!$B$12*SUM(税费参数!$B$9:税费参数!$B$10)/税费参数!$B$11)/(1+SUM(税费参数!$B$6:税费参数!$B$8)) -> 0.022081272 | G56: 0.024673913
A57: 川音 | B57: colour彼岸 | C57: 4 | D57: 3 | E57: =D57/C57 -> 0.75 | F57: =(G57-税费参数!$B$12*SUM(税费参数!$B$9:税费参数!$B$10)/税费参数!$B$11)/(1+SUM(税费参数!$B$6:税费参数!$B$8)) -> 0.019292854 | G57: 0.021794872
A58: 川音 | B58: 和谐公寓 | C58: 1 | D58: 0 | E58: =D58/C58 -> 0
A59: 川音 | B59: 大华世都 | C59: 1 | D59: 0 | E59: =D59/C59 -> 0
A60: 川音 | B60: 廊桥乐章 | C60: 1 | D60: 0 | E60: =D60/C60 -> 0
A61: 川音 | B61: 新南路84号 | C61: 1 | D61: 0 | E61: =D61/C61 -> 0
A62: 川音 | B62: 牡丹名苑 | C62: 2 | D62: 0 | E62: =D62/C62 -> 0
A63: 川音 | B63: 红星苑 | C63: 1 | D63: 0 | E63: =D63/C63 -> 0
A64: 川音 | B64: 美丽人生 | C64: 2 | D64: 0 | E64: =D64/C64 -> 0
A65: 川音 | B65: 锦宏骏苑北区 | C65: 2 | D65: 0 | E65: =D65/C65 -> 0
A66: 川音 | B66: 锦江新园 | C66: 1 | D66: 0 | E66: =D66/C66 -> 0
A67: 棕北 | B67: 花样年华梦想家 | C67: 15 | D67: 11 | E67: =D67/C67 -> 0.73333333 | F67: =(G67-税费参数!$B$12*SUM(税费参数!$B$9:税费参数!$B$10)/税费参数!$B$11)/(1+SUM(税费参数!$B$6:税费参数!$B$8)) -> 0.037297448 | G67: 0.040384615
A68: 棕北 | B68: 时代数码广场 | C68: 1 | D68: 1 | E68: =D68/C68 -> 1 | F68: =(G68-税费参数!$B$12*SUM(税费参数!$B$9:税费参数!$B$10)/税费参数!$B$11)/(1+SUM(税费参数!$B$6:税费参数!$B$8)) -> 0.033866446 | G68: 0.036842105
A69: 棕北 | B69: 新棕北 | C69: 6 | D69: 2 | E69: =D69/C69 -> 0.33333333 | F69: =(G69-税费参数!$B$12*SUM(税费参数!$B$9:税费参数!$B$10)/税费参数!$B$11)/(1+SUM(税费参数!$B$6:税费参数!$B$8)) -> 0.031670821 | G69: 0.034575123
A70: 棕北 | B70: 棕南公寓 | C70: 2 | D70: 2 | E70: =D70/C70 -> 1 | F70: =(G70-税费参数!$B$12*SUM(税费参数!$B$9:税费参数!$B$10)/税费参数!$B$11)/(1+SUM(税费参数!$B$6:税费参数!$B$8)) -> 0.031436642 | G70: 0.034333333
A71: 棕北 | B71: SOHO沸城 | C71: 4 | D71: 4 | E71: =D71/C71 -> 1 | F71: =(G71-税费参数!$B$12*SUM(税费参数!$B$9:税费参数!$B$10)/税费参数!$B$11)/(1+SUM(税费参数!$B$6:税费参数!$B$8)) -> 0.031140705 | G71: 0.034027778
A72: 棕北 | B72: 首航欣程 | C72: 7 | D72: 7 | E72: =D72/C72 -> 1 | F72: =(G72-税费参数!$B$12*SUM(税费参数!$B$9:税费参数!$B$10)/税费参数!$B$11)/(1+SUM(税费参数!$B$6:税费参数!$B$8)) -> 0.027078289 | G72: 0.029833333
A73: 棕北 | B73: 棕北国际 | C73: 3 | D73: 3 | E73: =D73/C73 -> 1 | F73: =(G73-税费参数!$B$12*SUM(税费参数!$B$9:税费参数!$B$10)/税费参数!$B$11)/(1+SUM(税费参数!$B$6:税费参数!$B$8)) -> 0.025521362 | G73: 0.028225806
A74: 玉林 | B74: 都市金岸 | C74: 4 | D74: 1 | E74: =D74/C74 -> 0.25 | F74: =(G74-税费参数!$B$12*SUM(税费参数!$B$9:税费参数!$B$10)/税费参数!$B$11)/(1+SUM(税费参数!$B$6:税费参数!$B$8)) -> 0.026302429 | G74: 0.029032258
A75: 玉林 | B75: 华宇蓉国府 | C75: 7 | D75: 7 | E75: =D75/C75 -> 1 | F75: =(G75-税费参数!$B$12*SUM(税费参数!$B$9:税费参数!$B$10)/税费参数!$B$11)/(1+SUM(税费参数!$B$6:税费参数!$B$8)) -> 0.022845485 | G75: 0.025462963
A76: 玉林 | B76: 祥福苑(武侯) | C76: 3 | D76: 0 | E76: =D76/C76 -> 0
A77: 盐市口 | B77: 大发百度城 | C77: 6 | D77: 3 | E77: =D77/C77 -> 0.5 | F77: =(G77-税费参数!$B$12*SUM(税费参数!$B$9:税费参数!$B$10)/税费参数!$B$11)/(1+SUM(税费参数!$B$6:税费参数!$B$8)) -> 0.030468119 | G77: 0.033333333
A78: 盐市口 | B78: 兴隆街23号 | C78: 3 | D78: 2 | E78: =D78/C78 -> 0.66666667 | F78: =(G78-税费参数!$B$12*SUM(税费参数!$B$9:税费参数!$B$10)/税费参数!$B$11)/(1+SUM(税费参数!$B$6:税费参数!$B$8)) -> 0.03030303 | G78: 0.033162879
A79: 盐市口 | B79: 缤舍 | C79: 4 | D79: 4 | E79: =D79/C79 -> 1 | F79: =(G79-税费参数!$B$12*SUM(税费参数!$B$9:税费参数!$B$10)/税费参数!$B$11)/(1+SUM(税费参数!$B$6:税费参数!$B$8)) -> 0.02901819 | G79: 0.031836281
A80: 盐市口 | B80: 科甲大厦 | C80: 16 | D80: 6 | E80: =D80/C80 -> 0.375 | F80: =(G80-税费参数!$B$12*SUM(税费参数!$B$9:税费参数!$B$10)/税费参数!$B$11)/(1+SUM(税费参数!$B$6:税费参数!$B$8)) -> 0.02722712 | G80: 0.029987001
A81: 盐市口 | B81: 新和春禧时代 | C81: 9 | D81: 5 | E81: =D81/C81 -> 0.55555556 | F81: =(G81-税费参数!$B$12*SUM(税费参数!$B$9:税费参数!$B$10)/税费参数!$B$11)/(1+SUM(税费参数!$B$6:税费参数!$B$8)) -> 0.026271186 | G81: 0.029
A82: 盐市口 | B82: 经典坐标 | C82: 10 | D82: 8 | E82: =D82/C82 -> 0.8 | F82: =(G82-税费参数!$B$12*SUM(税费参数!$B$9:税费参数!$B$10)/税费参数!$B$11)/(1+SUM(税费参数!$B$6:税费参数!$B$8)) -> 0.025916323 | G82: 0.028633603
A83: 盐市口 | B83: 萧邦 | C83: 15 | D83: 15 | E83: =D83/C83 -> 1 | F83: =(G83-税费参数!$B$12*SUM(税费参数!$B$9:税费参数!$B$10)/税费参数!$B$11)/(1+SUM(税费参数!$B$6:税费参数!$B$8)) -> 0.025646864 | G83: 0.028355388
A84: 盐市口 | B84: 都仕闲庭 | C84: 4 | D84: 2 | E84: =D84/C84 -> 0.5 | F84: =(G84-税费参数!$B$12*SUM(税费参数!$B$9:税费参数!$B$10)/税费参数!$B$11)/(1+SUM(税费参数!$B$6:税费参数!$B$8)) -> 0.025587523 | G84: 0.028294118
A85: 盐市口 | B85: 正成财富ID | C85: 18 | D85: 17 | E85: =D85/C85 -> 0.94444444 | F85: =(G85-税费参数!$B$12*SUM(税费参数!$B$9:税费参数!$B$10)/税费参数!$B$11)/(1+SUM(税费参数!$B$6:税费参数!$B$8)) -> 0.023821393 | G85: 0.026470588
A86: 盐市口 | B86: 现代之窗 | C86: 6 | D86: 3 | E86: =D86/C86 -> 0.5 | F86: =(G86-税费参数!$B$12*SUM(税费参数!$B$9:税费参数!$B$10)/税费参数!$B$11)/(1+SUM(税费参数!$B$6:税费参数!$B$8)) -> 0.023587901 | G86: 0.026229508
A87: 盐市口 | B87: 弘邦领邸 | C87: 3 | D87: 3 | E87: =D87/C87 -> 1 | F87: =(G87-税费参数!$B$12*SUM(税费参数!$B$9:税费参数!$B$10)/税费参数!$B$11)/(1+SUM(税费参数!$B$6:税费参数!$B$8)) -> 0.016183119 | G87: 0.018584071
A88: 盐市口 | B88: 都市驿站 | C88: 10 | D88: 9 | E88: =D88/C88 -> 0.9 | F88: =(G88-税费参数!$B$12*SUM(税费参数!$B$9:税费参数!$B$10)/税费参数!$B$11)/(1+SUM(税费参数!$B$6:税费参数!$B$8)) -> 0.015382091 | G88: 0.017757009
... A93: 盐市口 | B93: 美华大厦 | C93: 10 | D93: 9 | E93: =D93/C93 -> 0.9 | F93: =(G93-税费参数!$B$12*SUM(税费参数!$B$9:税费参数!$B$10)/税费参数!$B$11)/(1+SUM(税费参数!$B$6:税费参数!$B$8)) -> 0.011512318 | G93: 0.013761468
A94: 盐市口 | B94: 京都大厦 | C94: 5 | D94: 0 | E94: =D94/C94 -> 0
A95: 盐市口 | B95: 大地城市脉搏 | C95: 3 | D95: 0 | E95: =D95/C95 -> 0
A96: 盐市口 | B96: 梓潼桥西街18号 | C96: 1 | D96: 0 | E96: =D96/C96 -> 0
A97: 盐市口 | B97: 第一城 | C97: 1 | D97: 0 | E97: =D97/C97 -> 0
A98: 盐市口 | B98: 紫薇银座 | C98: 1 | D98: 0 | E98: =D98/C98 -> 0
A99: 盐市口 | B99: 自由天地 | C99: 2 | D99: 0 | E99: =D99/C99 -> 0
A100: 盐市口 | B100: 银杏地带 | C100: 2 | D100: 0 | E100: =D100/C100 -> 0
A101: 盐市口 | B101: 雕墅 | C101: 2 | D101: 0 | E101: =D101/C101 -> 0
A102: 西南财大 | B102: 金沙时代城 | C102: 4 | D102: 2 | E102: =D102/C102 -> 0.5 | F102: =(G102-税费参数!$B$12*SUM(税费参数!$B$9:税费参数!$B$10)/税费参数!$B$11)/(1+SUM(税费参数!$B$6:税费参数!$B$8)) -> 0.043842961 | G102: 0.047142857
A103: 西南财大 | B103: 仁和时代春天广场 | C103: 7 | D103: 5 | E103: =D103/C103 -> 0.71428571 | F103: =(G103-税费参数!$B$12*SUM(税费参数!$B$9:税费参数!$B$10)/税费参数!$B$11)/(1+SUM(税费参数!$B$6:税费参数!$B$8)) -> 0.036924939 | G103: 0.04
A104: 西南财大 | B104: 水木光华 | C104: 16 | D104: 12 | E104: =D104/C104 -> 0.75 | F104: =(G104-税费参数!$B$12*SUM(税费参数!$B$9:税费参数!$B$10)/税费参数!$B$11)/(1+SUM(税费参数!$B$6:税费参数!$B$8)) -> 0.030382841 | G104: 0.033245283
A105: 西南财大 | B105: 中华家园东区 | C105: 4 | D105: 3 | E105: =D105/C105 -> 0.75 | F105: =(G105-税费参数!$B$12*SUM(税费参数!$B$9:税费参数!$B$10)/税费参数!$B$11)/(1+SUM(税费参数!$B$6:税费参数!$B$8)) -> 0.028569055 | G105: 0.031372549
A106: 西南财大 | B106: 西财骏苑 | C106: 6 | D106: 2 | E106: =D106/C106 -> 0.33333333 | F106: =(G106-税费参数!$B$12*SUM(税费参数!$B$9:税费参数!$B$10)/税费参数!$B$11)/(1+SUM(税费参数!$B$6:税费参数!$B$8)) -> 0.027345974 | G106: 0.030109718
A107: 西南财大 | B107: 大陆西城秀筑 | C107: 5 | D107: 3 | E107: =D107/C107 -> 0.6 | F107: =(G107-税费参数!$B$12*SUM(税费参数!$B$9:税费参数!$B$10)/税费参数!$B$11)/(1+SUM(税费参数!$B$6:税费参数!$B$8)) -> 0.022632173 | G107: 0.025242718
A108: 西南财大 | B108: 光华馨地 | C108: 13 | D108: 13 | E108: =D108/C108 -> 1 | F108: =(G108-税费参数!$B$12*SUM(税费参数!$B$9:税费参数!$B$10)/税费参数!$B$11)/(1+SUM(税费参数!$B$6:税费参数!$B$8)) -> 0.018938084 | G108: 0.021428571
A109: 西南财大 | B109: 学府春 | C109: 5 | D109: 0 | E109: =D109/C109 -> 0
...

Sheet 户型汇总
A2: 各小区各面积户型成本调整后回报率
A3: 同商圈+小区+面积段+室厅数，出租面积相差≤15%；每套出售房源权重相同
A6: 商圈 | B6: 小区 | C6: 面积段 | D6: 室厅数 | E6: 出售数 | F6: 可匹配出售数 | G6: 匹配覆盖率 | H6: 出租候选数 | I6: 税费调整后回报率 | J6: 原毛回报率 | K6: 数据状态
A7: 华西 | B7: 丽景天成 | C7: 40–60㎡ | D7: 1室1厅 | E7: 2 | F7: 2 | G7: =F7/E7 -> 1 | H7: 2 | I7: =(J7-税费参数!$B$12*SUM(税费参数!$B$9:税费参数!$B$10)/税费参数!$B$11)/(1+SUM(税费参数!$B$6:税费参数!$B$8)) -> 0.020886241 | J7: 0.023440043 | K7: 可参考
A8: 华西 | B8: 丽景天成 | C8: 40–60㎡ | D8: 2室1厅 | E8: 2 | F8: 0 | G8: =F8/E8 -> 0 | H8: 0 | K8: 无匹配
A9: 华西 | B9: 丽景天成 | C9: 60–90㎡ | D9: 1室1厅 | E9: 2 | F9: 2 | G9: =F9/E9 -> 1 | H9: 1 | I9: =(J9-税费参数!$B$12*SUM(税费参数!$B$9:税费参数!$B$10)/税费参数!$B$11)/(1+SUM(税费参数!$B$6:税费参数!$B$8)) -> 0.018434955 | J9: 0.020909091 | K9: 低样本
A10: 华西 | B10: 丽景天成 | C10: 60–90㎡ | D10: 2室1厅 | E10: 3 | F10: 0 | G10: =F10/E10 -> 0 | H10: 0 | K10: 无匹配
A11: 华西 | B11: 人民南路三段16号 | C11: 60–90㎡ | D11: 2室1厅 | E11: 1 | F11: 0 | G11: =F11/E11 -> 0 | H11: 0 | K11: 无匹配
A12: 华西 | B12: 傲仕门 | C12: 40–60㎡ | D12: 1室1厅 | E12: 2 | F12: 2 | G12: =F12/E12 -> 1 | H12: 2 | I12: =(J12-税费参数!$B$12*SUM(税费参数!$B$9:税费参数!$B$10)/税费参数!$B$11)/(1+SUM(税费参数!$B$6:税费参数!$B$8)) -> 0.023671467 | J12: 0.026315789 | K12: 可参考
A13: 华西 | B13: 凯蒂阳光 | C13: 40–60㎡ | D13: 1室1厅 | E13: 2 | F13: 2 | G13: =F13/E13 -> 1 | H13: 2 | I13: =(J13-税费参数!$B$12*SUM(税费参数!$B$9:税费参数!$B$10)/税费参数!$B$11)/(1+SUM(税费参数!$B$6:税费参数!$B$8)) -> 0.02573794 | J13: 0.028449423 | K13: 可参考
A14: 华西 | B14: 城南世家 | C14: 60–90㎡ | D14: 2室1厅 | E14: 1 | F14: 1 | G14: =F14/E14 -> 1 | H14: 1 | I14: =(J14-税费参数!$B$12*SUM(税费参数!$B$9:税费参数!$B$10)/税费参数!$B$11)/(1+SUM(税费参数!$B$6:税费参数!$B$8)) -> 0.025453114 | J14: 0.02815534 | K14: 低样本
A15: 华西 | B15: 天乐嘉苑 | C15: 40–60㎡ | D15: 1室1厅 | E15: 1 | F15: 1 | G15: =F15/E15 -> 1 | H15: 1 | I15: =(J15-税费参数!$B$12*SUM(税费参数!$B$9:税费参数!$B$10)/税费参数!$B$11)/(1+SUM(税费参数!$B$6:税费参数!$B$8)) -> 0.029881136 | J15: 0.032727273 | K15: 低样本
A16: 华西 | B16: 天竺丽苑 | C16: 40–60㎡ | D16: 1室1厅 | E16: 1 | F16: 1 | G16: =F16/E16 -> 1 | H16: 1 | I16: =(J16-税费参数!$B$12*SUM(税费参数!$B$9:税费参数!$B$10)/税费参数!$B$11)/(1+SUM(税费参数!$B$6:税费参数!$B$8)) -> 0.026594027 | J16: 0.029333333 | K16: 低样本
A17: 华西 | B17: 天竺丽苑 | C17: 60–90㎡ | D17: 2室1厅 | E17: 1 | F17: 0 | G17: =F17/E17 -> 0 | H17: 1 | K17: 无匹配
A18: 华西 | B18: 米兰风度花园 | C18: 40–60㎡ | D18: 1室1厅 | E18: 1 | F18: 1 | G18: =F18/E18 -> 1 | H18: 2 | I18: =(J18-税费参数!$B$12*SUM(税费参数!$B$9:税费参数!$B$10)/税费参数!$B$11)/(1+SUM(税费参数!$B$6:税费参数!$B$8)) -> 0.02604564 | J18: 0.028767123 | K18: 低样本
A19: 华西 | B19: 米兰风度花园 | C19: 40–60㎡ | D19: 2室1厅 | E19: 1 | F19: 1 | G19: =F19/E19 -> 1 | H19: 1 | I19: =(J19-税费参数!$B$12*SUM(税费参数!$B$9:税费参数!$B$10)/税费参数!$B$11)/(1+SUM(税费参数!$B$6:税费参数!$B$8)) -> 0.023607748 | J19: 0.02625 | K19: 低样本
A20: 华西 | B20: 米兰风度花园 | C20: 60–90㎡ | D20: 2室1厅 | E20: 2 | F20: 2 | G20: =F20/E20 -> 1 | H20: 2 | I20: =(J20-税费参数!$B$12*SUM(税费参数!$B$9:税费参数!$B$10)/税费参数!$B$11)/(1+SUM(税费参数!$B$6:税费参数!$B$8)) -> 0.019399285 | J20: 0.021904762 | K20: 可参考
A21: 华西 | B21: 米兰风度花园 | C21: ≤40㎡ | D21: 1室1厅 | E21: 1 | F21: 0 | G21: =F21/E21 -> 0 | H21: 0 | K21: 无匹配
A22: 华西 | B22: 艺墅花乡 | C22: 40–60㎡ | D22: 1室0厅 | E22: 5 | F22: 5 | G22: =F22/E22 -> 1 | H22: 1 | I22: =(J22-税费参数!$B$12*SUM(税费参数!$B$9:税费参数!$B$10)/税费参数!$B$11)/(1+SUM(税费参数!$B$6:税费参数!$B$8)) -> 0.033251232 | J22: 0.036206897 | K22: 低样本
A23: 华西 | B23: 艺墅花乡 | C23: 40–60㎡ | D23: 1室1厅 | E23: 1 | F23: 0 | G23: =F23/E23 -> 0 | H23: 0 | K23: 无匹配
A24: 华西 | B24: 艺墅花乡 | C24: 40–60㎡ | D24: 2室1厅 | E24: 2 | F24: 2 | G24: =F24/E24 -> 1 | H24: 1 | I24: =(J24-税费参数!$B$12*SUM(税费参数!$B$9:税费参数!$B$10)/税费参数!$B$11)/(1+SUM(税费参数!$B$6:税费参数!$B$8)) -> 0.054565894 | J24: 0.058214286 | K24: 低样本
A25: 华西 | B25: 艺墅花乡 | C25: ≤40㎡ | D25: 1室1厅 | E25: 1 | F25: 0 | G25: =F25/E25 -> 0 | H25: 0 | K25: 无匹配
A26: 华西 | B26: 通祠路14号 | C26: 60–90㎡ | D26: 2室1厅 | E26: 1 | F26: 1 | G26: =F26/E26 -> 1 | H26: 1 | I26: =(J26-税费参数!$B$12*SUM(税费参数!$B$9:税费参数!$B$10)/税费参数!$B$11)/(1+SUM(税费参数!$B$6:税费参数!$B$8)) -> 0.020914661 | J26: 0.023469388 | K26: 低样本
A27: 华西 | B27: 金茂礼都 | C27: 40–60㎡ | D27: 1室1厅 | E27: 3 | F27: 3 | G27: =F27/E27 -> 1 | H27: 16 | I27: =(J27-税费参数!$B$12*SUM(税费参数!$B$9:税费参数!$B$10)/税费参数!$B$11)/(1+SUM(税费参数!$B$6:税费参数!$B$8)) -> 0.032004218 | J27: 0.034919355 | K27: 可参考
A28: 华西 | B28: 金茂礼都 | C28: 60–90㎡ | D28: 2室1厅 | E28: 2 | F28: 2 | G28: =F28/E28 -> 1 | H28: 3 | I28: =(J28-税费参数!$B$12*SUM(税费参数!$B$9:税费参数!$B$10)/税费参数!$B$11)/(1+SUM(税费参数!$B$6:税费参数!$B$8)) -> 0.026253838 | J28: 0.028982088 | K28: 可参考
A29: 华西 | B29: 金茂礼都 | C29: ≤40㎡ | D29: 1室1厅 | E29: 1 | F29: 1 | G29: =F29/E29 -> 1 | H29: 2 | I29: =(J29-税费参数!$B$12*SUM(税费参数!$B$9:税费参数!$B$10)/税费参数!$B$11)/(1+SUM(税费参数!$B$6:税费参数!$B$8)) -> 0.051012547 | J29: 0.054545455 | K29: 低样本
A30: 华西 | B30: 铜锣湾 | C30: 60–90㎡ | D30: 1室1厅 | E30: 1 | F30: 0 | G30: =F30/E30 -> 0 | H30: 0 | K30: 无匹配
A31: 华西 | B31: 锦和名邸 | C31: 60–90㎡ | D31: 2室1厅 | E31: 1 | F31: 0 | G31: =F31/E31 -> 0 | H31: 0 | K31: 无匹配
A32: 华西 | B32: 黉门公馆 | C32: 40–60㎡ | D32: 1室1厅 | E32: 2 | F32: 2 | G32: =F32/E32 -> 1 | H32: 8 | I32: =(J32-税费参数!$B$12*SUM(税费参数!$B$9:税费参数!$B$10)/税费参数!$B$11)/(1+SUM(税费参数!$B$6:税费参数!$B$8)) -> 0.02610878 | J32: 0.028832315 | K32: 可参考
A33: 华西 | B33: 黉门公馆 | C33: 60–90㎡ | D33: 1室1厅 | E33: 1 | F33: 0 | G33: =F33/E33 -> 0 | H33: 0 | K33: 无匹配
A34: 合江亭 | B34: SOHO我的寓所 | C34: 40–60㎡ | D34: 1室1厅 | E34: 2 | F34: 2 | G34: =F34/E34 -> 1 | H34: 2 | I34: =(J34-税费参数!$B$12*SUM(税费参数!$B$9:税费参数!$B$10)/税费参数!$B$11)/(1+SUM(税费参数!$B$6:税费参数!$B$8)) -> 0.026957224 | J34: 0.029708333 | K34: 可参考
A35: 合江亭 | B35: SOHO我的寓所 | C35: 40–60㎡ | D35: 2室1厅 | E35: 1 | F35: 0 | G35: =F35/E35 -> 0 | H35: 0 | K35: 无匹配
A36: 合江亭 | B36: SOHO我的寓所 | C36: ≤40㎡ | D36: 1室1厅 | E36: 3 | F36: 2 | G36: =F36/E36 -> 0.66666667 | H36: 2 | I36: =(J36-税费参数!$B$12*SUM(税费参数!$B$9:税费参数!$B$10)/税费参数!$B$11)/(1+SUM(税费参数!$B$6:税费参数!$B$8)) -> 0.022558055 | J36: 0.025166192 | K36: 可参考
A37: 合江亭 | B37: 三圣街21号 | C37: 60–90㎡ | D37: 2室1厅 | E37: 1 | F37: 0 | G37: =F37/E37 -> 0 | H37: 0 | K37: 无匹配
A38: 合江亭 | B38: 上东吉座 | C38: 40–60㎡ | D38: 1室1厅 | E38: 2 | F38: 1 | G38: =F38/E38 -> 0.5 | H38: 2 | I38: =(J38-税费参数!$B$12*SUM(税费参数!$B$9:税费参数!$B$10)/税费参数!$B$11)/(1+SUM(税费参数!$B$6:税费参数!$B$8)) -> 0.02039785 | J38: 0.02293578 | K38: 低样本
A39: 合江亭 | B39: 光辉岁月 | C39: 60–90㎡ | D39: 1室1厅 | E39: 3 | F39: 3 | G39: =F39/E39 -> 1 | H39: 1 | I39: =(J39-税费参数!$B$12*SUM(税费参数!$B$9:税费参数!$B$10)/税费参数!$B$11)/(1+SUM(税费参数!$B$6:税费参数!$B$8)) -> 0.019535549 | J39: 0.022045455 | K39: 低样本
A40: 合江亭 | B40: 光辉岁月 | C40: 60–90㎡ | D40: 2室1厅 | E40: 1 | F40: 0 | G40: =F40/E40 -> 0 | H40: 0 | K40: 无匹配
A41: 合江亭 | B41: 喜年广场 | C41: 40–60㎡ | D41: 1室0厅 | E41: 15 | F41: 15 | G41: =F41/E41 -> 1 | H41: 6 | I41: =(J41-税费参数!$B$12*SUM(税费参数!$B$9:税费参数!$B$10)/税费参数!$B$11)/(1+SUM(税费参数!$B$6:税费参数!$B$8)) -> 0.022166494 | J41: 0.024761905 | K41: 可参考
A42: 合江亭 | B42: 喜年广场 | C42: 40–60㎡ | D42: 1室1厅 | E42: 12 | F42: 12 | G42: =F42/E42 -> 1 | H42: 4 | I42: =(J42-税费参数!$B$12*SUM(税费参数!$B$9:税费参数!$B$10)/税费参数!$B$11)/(1+SUM(税费参数!$B$6:税费参数!$B$8)) -> 0.022281794 | J42: 0.024880952 | K42: 可参考
A43: 合江亭 | B43: 国际商务大厦 | C43: 40–60㎡ | D43: 1室0厅 | E43: 1 | F43: 1 | G43: =F43/E43 -> 1 | H43: 4 | I43: =(J43-税费参数!$B$12*SUM(税费参数!$B$9:税费参数!$B$10)/税费参数!$B$11)/(1+SUM(税费参数!$B$6:税费参数!$B$8)) -> 0.015793529 | J43: 0.018181818 | K43: 低样本
A44: 合江亭 | B44: 国际商务大厦 | C44: 40–60㎡ | D44: 1室1厅 | E44: 6 | F44: 4 | G44: =F44/E44 -> 0.66666667 | H44: 1 | I44: =(J44-税费参数!$B$12*SUM(税费参数!$B$9:税费参数!$B$10)/税费参数!$B$11)/(1+SUM(税费参数!$B$6:税费参数!$B$8)) -> 0.016990291 | J44: 0.019417476 | K44: 低样本
A45: 合江亭 | B45: 总府花园 | C45: 60–90㎡ | D45: 1室2厅 | E45: 1 | F45: 0 | G45: =F45/E45 -> 0 | H45: 0 | K45: 无匹配
A46: 合江亭 | B46: 总府花园 | C46: 60–90㎡ | D46: 2室1厅 | E46: 2 | F46: 2 | G46: =F46/E46 -> 1 | H46: 7 | I46: =(J46-税费参数!$B$12*SUM(税费参数!$B$9:税费参数!$B$10)/税费参数!$B$11)/(1+SUM(税费参数!$B$6:税费参数!$B$8)) -> 0.021198109 | J46: 0.023762047 | K46: 可参考
A47: 合江亭 | B47: 总府花园 | C47: 60–90㎡ | D47: 2室2厅 | E47: 1 | F47: 1 | G47: =F47/E47 -> 1 | H47: 2 | I47: =(J47-税费参数!$B$12*SUM(税费参数!$B$9:税费参数!$B$10)/税费参数!$B$11)/(1+SUM(税费参数!$B$6:税费参数!$B$8)) -> 0.034819455 | J47: 0.037826087 | K47: 低样本
A48: 合江亭 | B48: 星城银座 | C48: 40–60㎡ | D48: 1室0厅 | E48: 2 | F48: 2 | G48: =F48/E48 -> 1 | H48: 1 | I48: =(J48-税费参数!$B$12*SUM(税费参数!$B$9:税费参数!$B$10)/税费参数!$B$11)/(1+SUM(税费参数!$B$6:税费参数!$B$8)) -> 0.015476408 | J48: 0.017854391 | K48: 低样本
A49: 合江亭 | B49: 星城银座 | C49: 40–60㎡ | D49: 1室1厅 | E49: 6 | F49: 6 | G49: =F49/E49 -> 1 | H49: 4 | I49: =(J49-税费参数!$B$12*SUM(税费参数!$B$9:税费参数!$B$10)/税费参数!$B$11)/(1+SUM(税费参数!$B$6:税费参数!$B$8)) -> 0.020033736 | J49: 0.022559832 | K49: 可参考
A50: 合江亭 | B50: 星城银座 | C50: 40–60㎡ | D50: 2室1厅 | E50: 3 | F50: 3 | G50: =F50/E50 -> 1 | H50: 1 | I50: =(J50-税费参数!$B$12*SUM(税费参数!$B$9:税费参数!$B$10)/税费参数!$B$11)/(1+SUM(税费参数!$B$6:税费参数!$B$8)) -> 0.023017943 | J50: 0.025641026 | K50: 低样本
A51: 合江亭 | B51: 星城银座 | C51: ≤40㎡ | D51: 1室0厅 | E51: 4 | F51: 1 | G51: =F51/E51 -> 0.25 | H51: 1 | I51: =(J51-税费参数!$B$12*SUM(税费参数!$B$9:税费参数!$B$10)/税费参数!$B$11)/(1+SUM(税费参数!$B$6:税费参数!$B$8)) -> 0.016534982 | J51: 0.018947368 | K51: 低样本
A52: 合江亭 | B52: 星城银座 | C52: ≤40㎡ | D52: 1室1厅 | E52: 2 | F52: 2 | G52: =F52/E52 -> 1 | H52: 2 | I52: =(J52-税费参数!$B$12*SUM(税费参数!$B$9:税费参数!$B$10)/税费参数!$B$11)/(1+SUM(税费参数!$B$6:税费参数!$B$8)) -> 0.014511283 | J52: 0.016857899 | K52: 可参考
A53: 合江亭 | B53: 水岸银座 | C53: 40–60㎡ | D53: 1室1厅 | E53: 1 | F53: 0 | G53: =F53/E53 -> 0 | H53: 0 | K53: 无匹配
A54: 合江亭 | B54: 流星花园 | C54: 40–60㎡ | D54: 1室0厅 | E54: 4 | F54: 4 | G54: =F54/E54 -> 1 | H54: 2 | I54: =(J54-税费参数!$B$12*SUM(税费参数!$B$9:税费参数!$B$10)/税费参数!$B$11)/(1+SUM(税费参数!$B$6:税费参数!$B$8)) -> 0.025408612 | J54: 0.028109391 | K54: 可参考
A55: 合江亭 | B55: 流星花园 | C55: 40–60㎡ | D55: 1室1厅 | E55: 3 | F55: 2 | G55: =F55/E55 -> 0.66666667 | H55: 1 | I55: =(J55-税费参数!$B$12*SUM(税费参数!$B$9:税费参数!$B$10)/税费参数!$B$11)/(1+SUM(税费参数!$B$6:税费参数!$B$8)) -> 0.019418661 | J55: 0.021924768 | K55: 低样本
A56: 合江亭 | B56: 流星花园 | C56: 60–90㎡ | D56: 1室1厅 | E56: 1 | F56: 1 | G56: =F56/E56 -> 1 | H56: 1 | I56: =(J56-税费参数!$B$12*SUM(税费参数!$B$9:税费参数!$B$10)/税费参数!$B$11)/(1+SUM(税费参数!$B$6:税费参数!$B$8)) -> 0.024598283 | J56: 0.027272727 | K56: 低样本
A57: 合江亭 | B57: 流星花园 | C57: ≤40㎡ | D57: 1室0厅 | E57: 16 | F57: 16 | G57: =F57/E57 -> 1 | H57: 3 | I57: =(J57-税费参数!$B$12*SUM(税费参数!$B$9:税费参数!$B$10)/税费参数!$B$11)/(1+SUM(税费参数!$B$6:税费参数!$B$8)) -> 0.025856105 | J57: 0.028571429 | K57: 可参考
A58: 合江亭 | B58: 流星花园 | C58: ≤40㎡ | D58: 1室1厅 | E58: 2 | F58: 2 | G58: =F58/E58 -> 1 | H58: 2 | I58: =(J58-税费参数!$B$12*SUM(税费参数!$B$9:税费参数!$B$10)/税费参数!$B$11)/(1+SUM(税费参数!$B$6:税费参数!$B$8)) -> 0.025137778 | J58: 0.027829756 | K58: 可参考
A59: 合江亭 | B59: 美丽合江 | C59: 40–60㎡ | D59: 1室1厅 | E59: 3 | F59: 3 | G59: =F59/E59 -> 1 | H59: 4 | I59: =(J59-税费参数!$B$12*SUM(税费参数!$B$9:税费参数!$B$10)/税费参数!$B$11)/(1+SUM(税费参数!$B$6:税费参数!$B$8)) -> 0.017554479 | J59: 0.02 | K59: 可参考
A60: 合江亭 | B60: 蓉上坊一期 | C60: 40–60㎡ | D60: 1室1厅 | E60: 8 | F60: 8 | G60: =F60/E60 -> 1 | H60: 13 | I60: =(J60-税费参数!$B$12*SUM(税费参数!$B$9:税费参数!$B$10)/税费参数!$B$11)/(1+SUM(税费参数!$B$6:税费参数!$B$8)) -> 0.024086379 | J60: 0.026744186 | K60: 可参考
A61: 合江亭 | B61: 蓉上坊一期 | C61: 40–60㎡ | D61: 1室2厅 | E61: 1 | F61: 0 | G61: =F61/E61 -> 0 | H61: 0 | K61: 无匹配
A62: 合江亭 | B62: 蓉上坊一期 | C62: 60–90㎡ | D62: 1室1厅 | E62: 4 | F62: 4 | G62: =F62/E62 -> 1 | H62: 1 | I62: =(J62-税费参数!$B$12*SUM(税费参数!$B$9:税费参数!$B$10)/税费参数!$B$11)/(1+SUM(税费参数!$B$6:税费参数!$B$8)) -> 0.018472457 | J62: 0.020947811 | K62: 低样本
A63: 合江亭 | B63: 蓝光时代华章 | C63: 40–60㎡ | D63: 1室0厅 | E63: 1 | F63: 0 | G63: =F63/E63 -> 0 | H63: 0 | K63: 无匹配
A64: 合江亭 | B64: 蓝光时代华章 | C64: 40–60㎡ | D64: 1室1厅 | E64: 1 | F64: 0 | G64: =F64/E64 -> 0 | H64: 0 | K64: 无匹配
A65: 合江亭 | B65: 蓝光时代华章 | C65: ≤40㎡ | D65: 1室0厅 | E65: 16 | F65: 0 | G65: =F65/E65 -> 0 | H65: 0 | K65: 无匹配
A66: 合江亭 | B66: 蓝光时代华章 | C66: ≤40㎡ | D66: 1室1厅 | E66: 6 | F66: 0 | G66: =F66/E66 -> 0 | H66: 0 | K66: 无匹配
A67: 合江亭 | B67: 蓝光郁金香花园广场 | C67: 40–60㎡ | D67: 1室0厅 | E67: 2 | F67: 2 | G67: =F67/E67 -> 1 | H67: 3 | I67: =(J67-税费参数!$B$12*SUM(税费参数!$B$9:税费参数!$B$10)/税费参数!$B$11)/(1+SUM(税费参数!$B$6:税费参数!$B$8)) -> 0.017207369 | J67: 0.019641608 | K67: 可参考
A68: 合江亭 | B68: 蓝光郁金香花园广场 | C68: 40–60㎡ | D68: 1室1厅 | E68: 6 | F68: 6 | G68: =F68/E68 -> 1 | H68: 7 | I68: =(J68-税费参数!$B$12*SUM(税费参数!$B$9:税费参数!$B$10)/税费参数!$B$11)/(1+SUM(税费参数!$B$6:税费参数!$B$8)) -> 0.018972566 | J68: 0.021464174 | K68: 可参考
A69: 合江亭 | B69: 蓝光郁金香花园广场 | C69: ≤40㎡ | D69: 1室0厅 | E69: 2 | F69: 0 | G69: =F69/E69 -> 0 | H69: 0 | K69: 无匹配
A70: 合江亭 | B70: 银唐国际 | C70: 60–90㎡ | D70: 2室1厅 | E70: 1 | F70: 1 | G70: =F70/E70 -> 1 | H70: 5 | I70: =(J70-税费参数!$B$12*SUM(税费参数!$B$9:税费参数!$B$10)/税费参数!$B$11)/(1+SUM(税费参数!$B$6:税费参数!$B$8)) -> 0.020158911 | J70: 0.022689076 | K70: 低样本
A71: 合江亭 | B71: 锦上花 | C71: 40–60㎡ | D71: 1室0厅 | E71: 1 | F71: 1 | G71: =F71/E71 -> 1 | H71: 1 | I71: =(J71-税费参数!$B$12*SUM(税费参数!$B$9:税费参数!$B$10)/税费参数!$B$11)/(1+SUM(税费参数!$B$6:税费参数!$B$8)) -> 0.020244821 | J71: 0.022777778 | K71: 低样本
A72: 合江亭 | B72: 锦上花 | C72: 40–60㎡ | D72: 1室1厅 | E72: 13 | F72: 12 | G72: =F72/E72 -> 0.92307692 | H72: 4 | I72: =(J72-税费参数!$B$12*SUM(税费参数!$B$9:税费参数!$B$10)/税费参数!$B$11)/(1+SUM(税费参数!$B$6:税费参数!$B$8)) -> 0.019326413 | J72: 0.021829521 | K72: 可参考
A73: 合江亭 | B73: 锦上花 | C73: ≤40㎡ | D73: 1室0厅 | E73: 2 | F73: 0 | G73: =F73/E73 -> 0 | H73: 0 | K73: 无匹配
A74: 合江亭 | B74: 锦上花 | C74: ≤40㎡ | D74: 2室1厅 | E74: 1 | F74: 0 | G74: =F74/E74 -> 0 | H74: 0 | K74: 无匹配
A75: 合江亭 | B75: 锦江印象 | C75: 40–60㎡ | D75: 1室1厅 | E75: 15 | F75: 15 | G75: =F75/E75 -> 1 | H75: 15 | I75: =(J75-税费参数!$B$12*SUM(税费参数!$B$9:税费参数!$B$10)/税费参数!$B$11)/(1+SUM(税费参数!$B$6:税费参数!$B$8)) -> 0.017994717 | J75: 0.020454545 | K75: 可参考
A76: 合江亭 | B76: 锦江印象 | C76: ≤40㎡ | D76: 1室0厅 | E76: 1 | F76: 0 | G76: =F76/E76 -> 0 | H76: 0 | K76: 无匹配
A77: 合江亭 | B77: 锦江印象 | C77: ≤40㎡ | D77: 1室1厅 | E77: 1 | F77: 1 | G77: =F77/E77 -> 1 | H77: 1 | I77: =(J77-税费参数!$B$12*SUM(税费参数!$B$9:税费参数!$B$10)/税费参数!$B$11)/(1+SUM(税费参数!$B$6:税费参数!$B$8)) -> 0.018906921 | J77: 0.021396396 | K77: 低样本
A78: 合江亭 | B78: 龙瑞苑 | C78: 40–60㎡ | D78: 1室1厅 | E78: 1 | F78: 1 | G78: =F78/E78 -> 1 | H78: 1 | I78: =(J78-税费参数!$B$12*SUM(税费参数!$B$9:税费参数!$B$10)/税费参数!$B$11)/(1+SUM(税费参数!$B$6:税费参数!$B$8)) -> 0.027372384 | J78: 0.030136986 | K78: 低样本
A79: 川大 | B79: 中海格林威治城小户 | C79: 40–60㎡ | D79: 1室1厅 | E79: 3 | F79: 3 | G79: =F79/E79 -> 1 | H79: 1 | I79: =(J79-税费参数!$B$12*SUM(税费参数!$B$9:税费参数!$B$10)/税费参数!$B$11)/(1+SUM(税费参数!$B$6:税费参数!$B$8)) -> 0.028833481 | J79: 0.03164557 | K79: 低样本
A80: 川大 | B80: 和信派都 | C80: 40–60㎡ | D80: 1室1厅 | E80: 8 | F80: 8 | G80: =F80/E80 -> 1 | H80: 7 | I80: =(J80-税费参数!$B$12*SUM(税费参数!$B$9:税费参数!$B$10)/税费参数!$B$11)/(1+SUM(税费参数!$B$6:税费参数!$B$8)) -> 0.02584947 | J80: 0.028564578 | K80: 可参考
A81: 川大 | B81: 和信派都 | C81: 60–90㎡ | D81: 1室1厅 | E81: 1 | F81: 1 | G81: =F81/E81 -> 1 | H81: 4 | I81: =(J81-税费参数!$B$12*SUM(税费参数!$B$9:税费参数!$B$10)/税费参数!$B$11)/(1+SUM(税费参数!$B$6:税费参数!$B$8)) -> 0.021956857 | J81: 0.024545455 | K81: 低样本
A82: 川大 | B82: 和信派都 | C82: 60–90㎡ | D82: 2室1厅 | E82: 3 | F82: 3 | G82: =F82/E82 -> 1 | H82: 12 | I82: =(J82-税费参数!$B$12*SUM(税费参数!$B$9:税费参数!$B$10)/税费参数!$B$11)/(1+SUM(税费参数!$B$6:税费参数!$B$8)) -> 0.023405973 | J82: 0.026041667 | K82: 可参考
A83: 川大 | B83: 好望角 | C83: ≤40㎡ | D83: 1室0厅 | E83: 4 | F83: 4 | G83: =F83/E83 -> 1 | H83: 7 | I83: =(J83-税费参数!$B$12*SUM(税费参数!$B$9:税费参数!$B$10)/税费参数!$B$11)/(1+SUM(税费参数!$B$6:税费参数!$B$8)) -> 0.037910355 | J83: 0.041017442 | K83: 可参考
A84: 川大 | B84: 好望角 | C84: ≤40㎡ | D84: 1室1厅 | E84: 1 | F84: 1 | G84: =F84/E84 -> 1 | H84: 2 | I84: =(J84-税费参数!$B$12*SUM(税费参数!$B$9:税费参数!$B$10)/税费参数!$B$11)/(1+SUM(税费参数!$B$6:税费参数!$B$8)) -> 0.041767554 | J84: 0.045 | K84: 低样本
A85: 川大 | B85: 新时空公寓 | C85: 60–90㎡ | D85: 2室1厅 | E85: 1 | F85: 1 | G85: =F85/E85 -> 1 | H85: 3 | I85: =(J85-税费参数!$B$12*SUM(税费参数!$B$9:税费参数!$B$10)/税费参数!$B$11)/(1+SUM(税费参数!$B$6:税费参数!$B$8)) -> 0.017287913 | J85: 0.019724771 | K85: 低样本
A86: 川大 | B86: 新时空公寓 | C86: ≤40㎡ | D86: 1室0厅 | E86: 1 | F86: 1 | G86: =F86/E86 -> 1 | H86: 1 | I86: =(J86-税费参数!$B$12*SUM(税费参数!$B$9:税费参数!$B$10)/税费参数!$B$11)/(1+SUM(税费参数!$B$6:税费参数!$B$8)) -> 0.024972953 | J86: 0.027659574 | K86: 低样本
A87: 川大 | B87: 新时空公寓 | C87: ≤40㎡ | D87: 1室1厅 | E87: 1 | F87: 0 | G87: =F87/E87 -> 0 | H87: 0 | K87: 无匹配
A88: 川大 | B88: 棕榈花园 | C88: 40–60㎡ | D88: 1室1厅 | E88: 2 | F88: 2 | G88: =F88/E88 -> 1 | H88: 1 | I88: =(J88-税费参数!$B$12*SUM(税费参数!$B$9:税费参数!$B$10)/税费参数!$B$11)/(1+SUM(税费参数!$B$6:税费参数!$B$8)) -> 0.028357236 | J88: 0.031153846 | K88: 低样本
A89: 川大 | B89: 棕榈花园 | C89: 60–90㎡ | D89: 2室2厅 | E89: 1 | F89: 0 | G89: =F89/E89 -> 0 | H89: 0 | K89: 无匹配
A90: 川大 | B90: 樱花假日 | C90: 40–60㎡ | D90: 1室1厅 | E90: 4 | F90: 4 | G90: =F90/E90 -> 1 | H90: 3 | I90: =(J90-税费参数!$B$12*SUM(税费参数!$B$9:税费参数!$B$10)/税费参数!$B$11)/(1+SUM(税费参数!$B$6:税费参数!$B$8)) -> 0.030434511 | J90: 0.033298632 | K90: 可参考
A91: 川大 | B91: 樱花假日 | C91: 40–60㎡ | D91: 2室1厅 | E91: 2 | F91: 0 | G91: =F91/E91 -> 0 | H91: 0 | K91: 无匹配
A92: 川大 | B92: 樱花假日 | C92: 60–90㎡ | D92: 2室1厅 | E92: 7 | F92: 7 | G92: =F92/E92 -> 1 | H92: 3 | I92: =(J92-税费参数!$B$12*SUM(税费参数!$B$9:税费参数!$B$10)/税费参数!$B$11)/(1+SUM(税费参数!$B$6:税费参数!$B$8)) -> 0.029426697 | J92: 0.032258065 | K92: 可参考
A93: 川大 | B93: 樱花假日 | C93: ≤40㎡ | D93: 1室0厅 | E93: 3 | F93: 3 | G93: =F93/E93 -> 1 | H93: 5 | I93: =(J93-税费参数!$B$12*SUM(税费参数!$B$9:税费参数!$B$10)/税费参数!$B$11)/(1+SUM(税费参数!$B$6:税费参数!$B$8)) -> 0.034785179 | J93: 0.037790698 | K93: 可参考
A94: 川大 | B94: 樱花假日 | C94: ≤40㎡ | D94: 1室1厅 | E94: 3 | F94: 2 | G94: =F94/E94 -> 0.66666667 | H94: 2 | I94: =(J94-税费参数!$B$12*SUM(税费参数!$B$9:税费参数!$B$10)/税费参数!$B$11)/(1+SUM(税费参数!$B$6:税费参数!$B$8)) -> 0.034651109 | J94: 0.03765227 | K94: 可参考
A95: 川大 | B95: 海德花苑 | C95: 60–90㎡ | D95: 2室1厅 | E95: 2 | F95: 1 | G95: =F95/E95 -> 0.5 | H95: 1 | I95: =(J95-税费参数!$B$12*SUM(税费参数!$B$9:税费参数!$B$10)/税费参数!$B$11)/(1+SUM(税费参数!$B$6:税费参数!$B$8)) -> 0.014326069 | J95: 0.016666667 | K95: 低样本
A96: 川大 | B96: 纯真年代 | C96: 40–60㎡ | D96: 1室1厅 | E96: 6 | F96: 5 | G96: =F96/E96 -> 0.83333333 | H96: 1 | I96: =(J96-税费参数!$B$12*SUM(税费参数!$B$9:税费参数!$B$10)/税费参数!$B$11)/(1+SUM(税费参数!$B$6:税费参数!$B$8)) -> 0.022719935 | J96: 0.025333333 | K96: 低样本
A97: 川大 | B97: 蓝色加勒比广场 | C97: ≤40㎡ | D97: 1室0厅 | E97: 1 | F97: 1 | G97: =F97/E97 -> 1 | H97: 3 | I97: =(J97-税费参数!$B$12*SUM(税费参数!$B$9:税费参数!$B$10)/税费参数!$B$11)/(1+SUM(税费参数!$B$6:税费参数!$B$8)) -> 0.031544256 | J97: 0.034444444 | K97: 低样本
A98: 川大 | B98: 青年家园 | C98: 40–60㎡ | D98: 1室1厅 | E98: 1 | F98: 0 | G98: =F98/E98 -> 0 | H98: 0 | K98: 无匹配
A99: 川音 | B99: colour彼岸 | C99: 40–60㎡ | D99: 1室1厅 | E99: 1 | F99: 1 | G99: =F99/E99 -> 1 | H99: 2 | I99: =(J99-税费参数!$B$12*SUM(税费参数!$B$9:税费参数!$B$10)/税费参数!$B$11)/(1+SUM(税费参数!$B$6:税费参数!$B$8)) -> 0.019292854 | J99: 0.021794872 | K99: 低样本
A100: 川音 | B100: colour彼岸 | C100: 60–90㎡ | D100: 1室1厅 | E100: 1 | F100: 1 | G100: =F100/E100 -> 1 | H100: 1 | I100: =(J100-税费参数!$B$12*SUM(税费参数!$B$9:税费参数!$B$10)/税费参数!$B$11)/(1+SUM(税费参数!$B$6:税费参数!$B$8)) -> 0.018082765 | J100: 0.020545455 | K100: 低样本
A101: 川音 | B101: colour彼岸 | C101: 60–90㎡ | D101: 1室2厅 | E101: 1 | F101: 0 | G101: =F101/E101 -> 0 | H101: 0 | K101: 无匹配
A102: 川音 | B102: colour彼岸 | C102: 60–90㎡ | D102: 2室1厅 | E102: 1 | F102: 1 | G102: =F102/E102 -> 1 | H102: 3 | I102: =(J102-税费参数!$B$12*SUM(税费参数!$B$9:税费参数!$B$10)/税费参数!$B$11)/(1+SUM(税费参数!$B$6:税费参数!$B$8)) -> 0.020081061 | J102: 0.022608696 | K102: 低样本
A103: 川音 | B103: 临江路7号 | C103: 60–90㎡ | D103: 1室1厅 | E103: 2 | F103: 2 | G103: =F103/E103 -> 1 | H103: 3 | I103: =(J103-税费参数!$B$12*SUM(税费参数!$B$9:税费参数!$B$10)/税费参数!$B$11)/(1+SUM(税费参数!$B$6:税费参数!$B$8)) -> 0.025210061 | J103: 0.027904388 | K103: 可参考
...

Sheet 出售逐套
A2: 全部701套精装或简装出售房源
A3: 逐套成本调整后回报率取所有出租配对的中位数；无法匹配时留空
A6: 商圈 | B6: 小区 | C6: 面积段 | D6: 房型 | E6: 房源编号 | F6: 装修 | G6: 面积㎡ | H6: 售价万 | I6: 匹配出租数 | J6: 调整后回报率 | K6: 链接 | L6: 原毛回报率
A7: 华西 | B7: 丽景天成 | C7: 40–60㎡ | D7: 1室1厅 | E7: 106129412042.0 | F7: 精装 | G7: 57.93 | H7: 95 | I7: 2 | J7: =MEDIAN(租金配对!K9:K10) -> 0.021122722 | K7: https://cd.lianjia.com/ershoufang/106129412042.html | L7: =MEDIAN(租金配对!L9:L10) -> 0.023684211
A8: 华西 | B8: 丽景天成 | C8: 40–60㎡ | D8: 1室1厅 | E8: 106129483566.0 | F8: 简装 | G8: 59.3 | H8: 97 | I8: 2 | J8: =MEDIAN(租金配对!K7:K8) -> 0.020649759 | K8: https://cd.lianjia.com/ershoufang/106129483566.html | L8: =MEDIAN(租金配对!L7:L8) -> 0.023195876
A9: 华西 | B9: 丽景天成 | C9: 40–60㎡ | D9: 2室1厅 | E9: 106118664527.0 | F9: 精装 | G9: 56.34 | H9: 102 | I9: 0 | K9: https://cd.lianjia.com/ershoufang/106118664527.html
A10: 华西 | B10: 丽景天成 | C10: 40–60㎡ | D10: 2室1厅 | E10: 106127557823.0 | F10: 精装 | G10: 58.52 | H10: 117 | I10: 0 | K10: https://cd.lianjia.com/ershoufang/106127557823.html
A11: 华西 | B11: 丽景天成 | C11: 60–90㎡ | D11: 1室1厅 | E11: 106114386047.0 | F11: 简装 | G11: 60.74 | H11: 120 | I11: 1 | J11: =MEDIAN(租金配对!K12:K12) -> 0.017554479 | K11: https://cd.lianjia.com/ershoufang/106114386047.html | L11: =MEDIAN(租金配对!L12:L12) -> 0.02
A12: 华西 | B12: 丽景天成 | C12: 60–90㎡ | D12: 1室1厅 | E12: 106117140666.0 | F12: 精装 | G12: 60.74 | H12: 110 | I12: 1 | J12: =MEDIAN(租金配对!K11:K11) -> 0.01931543 | K12: https://cd.lianjia.com/ershoufang/106117140666.html | L12: =MEDIAN(租金配对!L11:L11) -> 0.021818182
A13: 华西 | B13: 丽景天成 | C13: 60–90㎡ | D13: 2室1厅 | E13: 106123825538.0 | F13: 精装 | G13: 60.4 | H13: 108 | I13: 0 | K13: https://cd.lianjia.com/ershoufang/106123825538.html
A14: 华西 | B14: 丽景天成 | C14: 60–90㎡ | D14: 2室1厅 | E14: 106128883747.0 | F14: 简装 | G14: 75.8 | H14: 112 | I14: 0 | K14: https://cd.lianjia.com/ershoufang/106128883747.html
A15: 华西 | B15: 丽景天成 | C15: 60–90㎡ | D15: 2室1厅 | E15: 106128956197.0 | F15: 简装 | G15: 75.8 | H15: 108 | I15: 0 | K15: https://cd.lianjia.com/ershoufang/106128956197.html
A16: 华西 | B16: 人民南路三段16号 | C16: 60–90㎡ | D16: 2室1厅 | E16: 106127607383.0 | F16: 简装 | G16: 77 | H16: 110 | I16: 0 | K16: https://cd.lianjia.com/ershoufang/106127607383.html
A17: 华西 | B17: 傲仕门 | C17: 40–60㎡ | D17: 1室1厅 | E17: 106121807884.0 | F17: 精装 | G17: 55.41 | H17: 95 | I17: 2 | J17: =MEDIAN(租金配对!K13:K14) -> 0.023671467 | K17: https://cd.lianjia.com/ershoufang/106121807884.html | L17: =MEDIAN(租金配对!L13:L14) -> 0.026315789
A18: 华西 | B18: 傲仕门 | C18: 40–60㎡ | D18: 1室1厅 | E18: 106123379786.0 | F18: 精装 | G18: 59.44 | H18: 95 | I18: 2 | J18: =MEDIAN(租金配对!K15:K16) -> 0.023671467 | K18: https://cd.lianjia.com/ershoufang/106123379786.html | L18: =MEDIAN(租金配对!L15:L16) -> 0.026315789
A19: 华西 | B19: 凯蒂阳光 | C19: 40–60㎡ | D19: 1室1厅 | E19: 106123405462.0 | F19: 简装 | G19: 51.94 | H19: 98 | I19: 2 | J19: =MEDIAN(租金配对!K17:K18) -> 0.024867816 | K19: https://cd.lianjia.com/ershoufang/106123405462.html | L19: =MEDIAN(租金配对!L17:L18) -> 0.02755102
A20: 华西 | B20: 凯蒂阳光 | C20: 40–60㎡ | D20: 1室1厅 | E20: 106127993289.0 | F20: 简装 | G20: 48.56 | H20: 92 | I20: 2 | J20: =MEDIAN(租金配对!K19:K20) -> 0.026608064 | K20: https://cd.lianjia.com/ershoufang/106127993289.html | L20: =MEDIAN(租金配对!L19:L20) -> 0.029347826
A21: 华西 | B21: 城南世家 | C21: 60–90㎡ | D21: 2室1厅 | E21: 106129068792.0 | F21: 简装 | G21: 68.61 | H21: 103 | I21: 1 | J21: =MEDIAN(租金配对!K21:K21) -> 0.025453114 | K21: https://cd.lianjia.com/ershoufang/106129068792.html | L21: =MEDIAN(租金配对!L21:L21) -> 0.02815534
A22: 华西 | B22: 天乐嘉苑 | C22: 40–60㎡ | D22: 1室1厅 | E22: 106127114539.0 | F22: 简装 | G22: 44.29 | H22: 55 | I22: 1 | J22: =MEDIAN(租金配对!K22:K22) -> 0.029881136 | K22: https://cd.lianjia.com/ershoufang/106127114539.html | L22: =MEDIAN(租金配对!L22:L22) -> 0.032727273
A23: 华西 | B23: 天竺丽苑 | C23: 40–60㎡ | D23: 1室1厅 | E23: 106129150378.0 | F23: 简装 | G23: 47.04 | H23: 75 | I23: 1 | J23: =MEDIAN(租金配对!K23:K23) -> 0.026594027 | K23: https://cd.lianjia.com/ershoufang/106129150378.html | L23: =MEDIAN(租金配对!L23:L23) -> 0.029333333
A24: 华西 | B24: 天竺丽苑 | C24: 60–90㎡ | D24: 2室1厅 | E24: 106129574000.0 | F24: 精装 | G24: 61.5 | H24: 91 | I24: 0 | K24: https://cd.lianjia.com/ershoufang/106129574000.html
A25: 华西 | B25: 米兰风度花园 | C25: 40–60㎡ | D25: 1室1厅 | E25: 106124158582.0 | F25: 简装 | G25: 52.51 | H25: 73 | I25: 2 | J25: =MEDIAN(租金配对!K24:K25) -> 0.02604564 | K25: https://cd.lianjia.com/ershoufang/106124158582.html | L25: =MEDIAN(租金配对!L24:L25) -> 0.028767123
A26: 华西 | B26: 米兰风度花园 | C26: 40–60㎡ | D26: 2室1厅 | E26: 106127339364.0 | F26: 精装 | G26: 52.51 | H26: 80 | I26: 1 | J26: =MEDIAN(租金配对!K26:K26) -> 0.023607748 | K26: https://cd.lianjia.com/ershoufang/106127339364.html | L26: =MEDIAN(租金配对!L26:L26) -> 0.02625
A27: 华西 | B27: 米兰风度花园 | C27: 60–90㎡ | D27: 2室1厅 | E27: 106127189136.0 | F27: 精装 | G27: 69.69 | H27: 105 | I27: 2 | J27: =MEDIAN(租金配对!K29:K30) -> 0.019399285 | K27: https://cd.lianjia.com/ershoufang/106127189136.html | L27: =MEDIAN(租金配对!L29:L30) -> 0.021904762
A28: 华西 | B28: 米兰风度花园 | C28: 60–90㎡ | D28: 2室1厅 | E28: 106128046504.0 | F28: 简装 | G28: 69.88 | H28: 105 | I28: 2 | J28: =MEDIAN(租金配对!K27:K28) -> 0.019399285 | K28: https://cd.lianjia.com/ershoufang/106128046504.html | L28: =MEDIAN(租金配对!L27:L28) -> 0.021904762
A29: 华西 | B29: 米兰风度花园 | C29: ≤40㎡ | D29: 1室1厅 | E29: 106115572764.0 | F29: 简装 | G29: 37.07 | H29: 75 | I29: 0 | K29: https://cd.lianjia.com/ershoufang/106115572764.html
A30: 华西 | B30: 艺墅花乡 | C30: 40–60㎡ | D30: 1室0厅 | E30: 106115608951.0 | F30: 精装 | G30: 41.74 | H30: 50 | I30: 1 | J30: =MEDIAN(租金配对!K33:K33) -> 0.038861985 | K30: https://cd.lianjia.com/ershoufang/106115608951.html | L30: =MEDIAN(租金配对!L33:L33) -> 0.042
A31: 华西 | B31: 艺墅花乡 | C31: 40–60㎡ | D31: 1室0厅 | E31: 106124681209.0 | F31: 简装 | G31: 48.01 | H31: 59.8 | I31: 1 | J31: =MEDIAN(租金配对!K32:K32) -> 0.032195697 | K31: https://cd.lianjia.com/ershoufang/106124681209.html | L31: =MEDIAN(租金配对!L32:L32) -> 0.035117057
A32: 华西 | B32: 艺墅花乡 | C32: 40–60㎡ | D32: 1室0厅 | E32: 106124773262.0 | F32: 简装 | G32: 47.97 | H32: 58 | I32: 1 | J32: =MEDIAN(租金配对!K35:K35) -> 0.033251232 | K32: https://cd.lianjia.com/ershoufang/106124773262.html | L32: =MEDIAN(租金配对!L35:L35) -> 0.036206897
A33: 华西 | B33: 艺墅花乡 | C33: 40–60㎡ | D33: 1室0厅 | E33: 106124773286.0 | F33: 简装 | G33: 47.97 | H33: 63 | I33: 1 | J33: =MEDIAN(租金配对!K34:K34) -> 0.030468119 | K33: https://cd.lianjia.com/ershoufang/106124773286.html | L33: =MEDIAN(租金配对!L34:L34) -> 0.033333333
A34: 华西 | B34: 艺墅花乡 | C34: 40–60㎡ | D34: 1室0厅 | E34: 106126498573.0 | F34: 简装 | G34: 47.97 | H34: 58 | I34: 1 | J34: =MEDIAN(租金配对!K31:K31) -> 0.033251232 | K34: https://cd.lianjia.com/ershoufang/106126498573.html | L34: =MEDIAN(租金配对!L31:L31) -> 0.036206897
A35: 华西 | B35: 艺墅花乡 | C35: 40–60㎡ | D35: 1室1厅 | E35: 106123148784.0 | F35: 精装 | G35: 44.72 | H35: 77.8 | I35: 0 | K35: https://cd.lianjia.com/ershoufang/106123148784.html
A36: 华西 | B36: 艺墅花乡 | C36: 40–60㎡ | D36: 2室1厅 | E36: 106116981602.0 | F36: 简装 | G36: 42.17 | H36: 63 | I36: 1 | J36: =MEDIAN(租金配对!K37:K37) -> 0.067364234 | K36: https://cd.lianjia.com/ershoufang/106116981602.html | L36: =MEDIAN(租金配对!L37:L37) -> 0.071428571
A37: 华西 | B37: 艺墅花乡 | C37: 40–60㎡ | D37: 2室1厅 | E37: 106118801081.0 | F37: 简装 | G37: 53.95 | H37: 100 | I37: 1 | J37: =MEDIAN(租金配对!K36:K36) -> 0.041767554 | K37: https://cd.lianjia.com/ershoufang/106118801081.html | L37: =MEDIAN(租金配对!L36:L36) -> 0.045
A38: 华西 | B38: 艺墅花乡 | C38: ≤40㎡ | D38: 1室1厅 | E38: 106128828442.0 | F38: 简装 | G38: 35.66 | H38: 68 | I38: 0 | K38: https://cd.lianjia.com/ershoufang/106128828442.html
A39: 华西 | B39: 通祠路14号 | C39: 60–90㎡ | D39: 2室1厅 | E39: 106128171374.0 | F39: 简装 | G39: 82.74 | H39: 98 | I39: 1 | J39: =MEDIAN(租金配对!K38:K38) -> 0.020914661 | K39: https://cd.lianjia.com/ershoufang/106128171374.html | L39: =MEDIAN(租金配对!L38:L38) -> 0.023469388
A40: 华西 | B40: 金茂礼都 | C40: 40–60㎡ | D40: 1室1厅 | E40: 106120376840.0 | F40: 简装 | G40: 44.51 | H40: 61 | I40: 16 | J40: =MEDIAN(租金配对!K41:K56) -> 0.032558647 | K40: https://cd.lianjia.com/ershoufang/106120376840.html | L40: =MEDIAN(租金配对!L41:L56) -> 0.035491803
A41: 华西 | B41: 金茂礼都 | C41: 40–60㎡ | D41: 1室1厅 | E41: 106129590974.0 | F41: 精装 | G41: 44.14 | H41: 62 | I41: 16 | J41: =MEDIAN(租金配对!K73:K88) -> 0.032004218 | K41: https://cd.lianjia.com/ershoufang/106129590974.html | L41: =MEDIAN(租金配对!L73:L88) -> 0.034919355
A42: 华西 | B42: 金茂礼都 | C42: 40–60㎡ | D42: 1室1厅 | E42: 106129626353.0 | F42: 简装 | G42: 48.73 | H42: 70 | I42: 16 | J42: =MEDIAN(租金配对!K57:K72) -> 0.028139052 | K42: https://cd.lianjia.com/ershoufang/106129626353.html | L42: =MEDIAN(租金配对!L57:L72) -> 0.030928571
A43: 华西 | B43: 金茂礼都 | C43: 60–90㎡ | D43: 2室1厅 | E43: 106123772639.0 | F43: 精装 | G43: 63.43 | H43: 109 | I43: 2 | J43: =MEDIAN(租金配对!K91:K92) -> 0.025729169 | K43: https://cd.lianjia.com/ershoufang/106123772639.html | L43: =MEDIAN(租金配对!L91:L92) -> 0.028440367
A44: 华西 | B44: 金茂礼都 | C44: 60–90㎡ | D44: 2室1厅 | E44: 106125667483.0 | F44: 简装 | G44: 62.96 | H44: 105 | I44: 2 | J44: =MEDIAN(租金配对!K89:K90) -> 0.026778508 | K44: https://cd.lianjia.com/ershoufang/106125667483.html | L44: =MEDIAN(租金配对!L89:L90) -> 0.02952381
A45: 华西 | B45: 金茂礼都 | C45: ≤40㎡ | D45: 1室1厅 | E45: 106125923205.0 | F45: 简装 | G45: 31.03 | H45: 44 | I45: 2 | J45: =MEDIAN(租金配对!K39:K40) -> 0.051012547 | K45: https://cd.lianjia.com/ershoufang/106125923205.html | L45: =MEDIAN(租金配对!L39:L40) -> 0.054545455
A46: 华西 | B46: 铜锣湾 | C46: 60–90㎡ | D46: 1室1厅 | E46: 106127877602.0 | F46: 简装 | G46: 63.74 | H46: 89 | I46: 0 | K46: https://cd.lianjia.com/ershoufang/106127877602.html
A47: 华西 | B47: 锦和名邸 | C47: 60–90㎡ | D47: 2室1厅 | E47: 106123690105.0 | F47: 精装 | G47: 82.86 | H47: 118 | I47: 0 | K47: https://cd.lianjia.com/ershoufang/106123690105.html
A48: 华西 | B48: 黉门公馆 | C48: 40–60㎡ | D48: 1室1厅 | E48: 106128591031.0 | F48: 精装 | G48: 50.09 | H48: 85 | I48: 8 | J48: =MEDIAN(租金配对!K101:K108) -> 0.024909557 | K48: https://cd.lianjia.com/ershoufang/106128591031.html | L48: =MEDIAN(租金配对!L101:L108) -> 0.027594118
A49: 华西 | B49: 黉门公馆 | C49: 40–60㎡ | D49: 1室1厅 | E49: 106129666723.0 | F49: 简装 | G49: 50.09 | H49: 78 | I49: 8 | J49: =MEDIAN(租金配对!K93:K100) -> 0.027308003 | K49: https://cd.lianjia.com/ershoufang/106129666723.html | L49: =MEDIAN(租金配对!L93:L100) -> 0.030070513
A50: 华西 | B50: 黉门公馆 | C50: 60–90㎡ | D50: 1室1厅 | E50: 106128845713.0 | F50: 简装 | G50: 62.19 | H50: 98 | I50: 0 | K50: https://cd.lianjia.com/ershoufang/106128845713.html
A51: 合江亭 | B51: SOHO我的寓所 | C51: 40–60㎡ | D51: 1室1厅 | E51: 106121997017.0 | F51: 精装 | G51: 42.99 | H51: 75 | I51: 2 | J51: =MEDIAN(租金配对!K115:K116) -> 0.027885391 | K51: https://cd.lianjia.com/ershoufang/106121997017.html | L51: =MEDIAN(租金配对!L115:L116) -> 0.030666667
A52: 合江亭 | B52: SOHO我的寓所 | C52: 40–60㎡ | D52: 1室1厅 | E52: 106125480592.0 | F52: 精装 | G52: 48.75 | H52: 80 | I52: 2 | J52: =MEDIAN(租金配对!K113:K114) -> 0.026029056 | K52: https://cd.lianjia.com/ershoufang/106125480592.html | L52: =MEDIAN(租金配对!L113:L114) -> 0.02875
A53: 合江亭 | B53: SOHO我的寓所 | C53: 40–60㎡ | D53: 2室1厅 | E53: 106123996551.0 | F53: 简装 | G53: 48.68 | H53: 80 | I53: 0 | K53: https://cd.lianjia.com/ershoufang/106123996551.html
A54: 合江亭 | B54: SOHO我的寓所 | C54: ≤40㎡ | D54: 1室1厅 | E54: 106118513855.0 | F54: 精装 | G54: 36.81 | H54: 81 | I54: 2 | J54: =MEDIAN(租金配对!K109:K110) -> 0.022098168 | K54: https://cd.lianjia.com/ershoufang/106118513855.html | L54: =MEDIAN(租金配对!L109:L110) -> 0.024691358
A55: 合江亭 | B55: SOHO我的寓所 | C55: ≤40㎡ | D55: 1室1厅 | E55: 106122115277.0 | F55: 精装 | G55: 36.84 | H55: 78 | I55: 2 | J55: =MEDIAN(租金配对!K111:K112) -> 0.023017943 | K55: https://cd.lianjia.com/ershoufang/106122115277.html | L55: =MEDIAN(租金配对!L111:L112) -> 0.025641026
A56: 合江亭 | B56: SOHO我的寓所 | C56: ≤40㎡ | D56: 1室1厅 | E56: 106125247948.0 | F56: 精装 | G56: 28.01 | H56: 55 | I56: 0 | K56: https://cd.lianjia.com/ershoufang/106125247948.html
A57: 合江亭 | B57: 三圣街21号 | C57: 60–90㎡ | D57: 2室1厅 | E57: 106127907978.0 | F57: 简装 | G57: 65.63 | H57: 116 | I57: 0 | K57: https://cd.lianjia.com/ershoufang/106127907978.html
A58: 合江亭 | B58: 上东吉座 | C58: 40–60㎡ | D58: 1室1厅 | E58: 106117846657.0 | F58: 简装 | G58: 59.66 | H58: 109 | I58: 2 | J58: =MEDIAN(租金配对!K117:K118) -> 0.02039785 | K58: https://cd.lianjia.com/ershoufang/106117846657.html | L58: =MEDIAN(租金配对!L117:L118) -> 0.02293578
A59: 合江亭 | B59: 上东吉座 | C59: 40–60㎡ | D59: 1室1厅 | E59: 106120793853.0 | F59: 简装 | G59: 50.57 | H59: 93 | I59: 0 | K59: https://cd.lianjia.com/ershoufang/106120793853.html
A60: 合江亭 | B60: 光辉岁月 | C60: 60–90㎡ | D60: 1室1厅 | E60: 106123066465.0 | F60: 简装 | G60: 65.51 | H60: 86 | I60: 1 | J60: =MEDIAN(租金配对!K119:K119) -> 0.020032096 | K60: https://cd.lianjia.com/ershoufang/106123066465.html | L60: =MEDIAN(租金配对!L119:L119) -> 0.02255814
A61: 合江亭 | B61: 光辉岁月 | C61: 60–90㎡ | D61: 1室1厅 | E61: 106125395931.0 | F61: 简装 | G61: 60.6 | H61: 88 | I61: 1 | J61: =MEDIAN(租金配对!K120:K120) -> 0.019535549 | K61: https://cd.lianjia.com/ershoufang/106125395931.html | L61: =MEDIAN(租金配对!L120:L120) -> 0.022045455
A62: 合江亭 | B62: 光辉岁月 | C62: 60–90㎡ | D62: 1室1厅 | E62: 106129410929.0 | F62: 精装 | G62: 70.66 | H62: 108 | I62: 1 | J62: =MEDIAN(租金配对!K121:K121) -> 0.015581562 | K62: https://cd.lianjia.com/ershoufang/106129410929.html | L62: =MEDIAN(租金配对!L121:L121) -> 0.017962963
A63: 合江亭 | B63: 光辉岁月 | C63: 60–90㎡ | D63: 2室1厅 | E63: 106114939316.0 | F63: 精装 | G63: 65.74 | H63: 102 | I63: 0 | K63: https://cd.lianjia.com/ershoufang/106114939316.html
A64: 合江亭 | B64: 喜年广场 | C64: 40–60㎡ | D64: 1室0厅 | E64: 106124080499.0 | F64: 精装 | G64: 47.39 | H64: 105.5 | I64: 6 | J64: =MEDIAN(租金配对!K200:K205) -> 0.022052833 | K64: https://cd.lianjia.com/ershoufang/106124080499.html | L64: =MEDIAN(租金配对!L200:L205) -> 0.02464455
A65: 合江亭 | B65: 喜年广场 | C65: 40–60㎡ | D65: 1室0厅 | E65: 106124795179.0 | F65: 精装 | G65: 47.06 | H65: 116 | I65: 6 | J65: =MEDIAN(租金配对!K140:K145) -> 0.019892294 | K65: https://cd.lianjia.com/ershoufang/106124795179.html | L65: =MEDIAN(租金配对!L140:L145) -> 0.022413793
A66: 合江亭 | B66: 喜年广场 | C66: 40–60㎡ | D66: 1室0厅 | E66: 106126426079.0 | F66: 精装 | G66: 46.76 | H66: 108 | I66: 6 | J66: =MEDIAN(租金配对!K146:K151) -> 0.021500314 | K66: https://cd.lianjia.com/ershoufang/106126426079.html | L66: =MEDIAN(租金配对!L146:L151) -> 0.024074074
A67: 合江亭 | B67: 喜年广场 | C67: 40–60㎡ | D67: 1室0厅 | E67: 106127039198.0 | F67: 精装 | G67: 46.76 | H67: 100 | I67: 6 | J67: =MEDIAN(租金配对!K152:K157) -> 0.023365617 | K67: https://cd.lianjia.com/ershoufang/106127039198.html | L67: =MEDIAN(租金配对!L152:L157) -> 0.026
A68: 合江亭 | B68: 喜年广场 | C68: 40–60㎡ | D68: 1室0厅 | E68: 106127475947.0 | F68: 精装 | G68: 47.48 | H68: 100 | I68: 6 | J68: =MEDIAN(租金配对!K194:K199) -> 0.023365617 | K68: https://cd.lianjia.com/ershoufang/106127475947.html | L68: =MEDIAN(租金配对!L194:L199) -> 0.026
A69: 合江亭 | B69: 喜年广场 | C69: 40–60㎡ | D69: 1室0厅 | E69: 106127808775.0 | F69: 精装 | G69: 46.81 | H69: 86 | I69: 6 | J69: =MEDIAN(租金配对!K122:K127) -> 0.027464947 | K69: https://cd.lianjia.com/ershoufang/106127808775.html | L69: =MEDIAN(租金配对!L122:L127) -> 0.030232558
A70: 合江亭 | B70: 喜年广场 | C70: 40–60㎡ | D70: 1室0厅 | E70: 106127851126.0 | F70: 精装 | G70: 46.83 | H70: 103 | I70: 6 | J70: =MEDIAN(租金配对!K164:K169) -> 0.022632173 | K70: https://cd.lianjia.com/ershoufang/106127851126.html | L70: =MEDIAN(租金配对!L164:L169) -> 0.025242718
A71: 合江亭 | B71: 喜年广场 | C71: 40–60㎡ | D71: 1室0厅 | E71: 106127876380.0 | F71: 精装 | G71: 46.76 | H71: 115 | I71: 6 | J71: =MEDIAN(租金配对!K182:K187) -> 0.020081061 | K71: https://cd.lianjia.com/ershoufang/106127876380.html | L71: =MEDIAN(租金配对!L182:L187) -> 0.022608696
A72: 合江亭 | B72: 喜年广场 | C72: 40–60㎡ | D72: 1室0厅 | E72: 106128104483.0 | F72: 精装 | G72: 46.15 | H72: 93 | I72: 6 | J72: =MEDIAN(租金配对!K128:K133) -> 0.025261007 | K72: https://cd.lianjia.com/ershoufang/106128104483.html | L72: =MEDIAN(租金配对!L128:L133) -> 0.027956989
A73: 合江亭 | B73: 喜年广场 | C73: 40–60㎡ | D73: 1室0厅 | E73: 106128363014.0 | F73: 精装 | G73: 47.03 | H73: 94.5 | I73: 6 | J73: =MEDIAN(租金配对!K134:K139) -> 0.024831213 | K73: https://cd.lianjia.com/ershoufang/106128363014.html | L73: =MEDIAN(租金配对!L134:L139) -> 0.027513228
A74: 合江亭 | B74: 喜年广场 | C74: 40–60㎡ | D74: 1室0厅 | E74: 106128593594.0 | F74: 简装 | G74: 47.48 | H74: 110 | I74: 6 | J74: =MEDIAN(租金配对!K170:K175) -> 0.021076381 | K74: https://cd.lianjia.com/ershoufang/106128593594.html | L74: =MEDIAN(租金配对!L170:L175) -> 0.023636364
A75: 合江亭 | B75: 喜年广场 | C75: 40–60㎡ | D75: 1室0厅 | E75: 106129248033.0 | F75: 精装 | G75: 46.57 | H75: 95 | I75: 6 | J75: =MEDIAN(租金配对!K188:K193) -> 0.024690965 | K75: https://cd.lianjia.com/ershoufang/106129248033.html | L75: =MEDIAN(租金配对!L188:L193) -> 0.027368421
A76: 合江亭 | B76: 喜年广场 | C76: 40–60㎡ | D76: 1室0厅 | E76: 106129248063.0 | F76: 精装 | G76: 46.84 | H76: 105 | I76: 6 | J76: =MEDIAN(租金配对!K158:K163) -> 0.022166494 | K76: https://cd.lianjia.com/ershoufang/106129248063.html | L76: =MEDIAN(租金配对!L158:L163) -> 0.024761905
A77: 合江亭 | B77: 喜年广场 | C77: 40–60㎡ | D77: 1室0厅 | E77: 106129332186.0 | F77: 精装 | G77: 46.89 | H77: 105 | I77: 6 | J77: =MEDIAN(租金配对!K176:K181) -> 0.022166494 | K77: https://cd.lianjia.com/ershoufang/106129332186.html | L77: =MEDIAN(租金配对!L176:L181) -> 0.024761905
A78: 合江亭 | B78: 喜年广场 | C78: 40–60㎡ | D78: 1室0厅 | E78: 106129694247.0 | F78: 精装 | G78: 46.89 | H78: 105 | I78: 6 | J78: =MEDIAN(租金配对!K206:K211) -> 0.022166494 | K78: https://cd.lianjia.com/ershoufang/106129694247.html | L78: =MEDIAN(租金配对!L206:L211) -> 0.024761905
A79: 合江亭 | B79: 喜年广场 | C79: 40–60㎡ | D79: 1室1厅 | E79: 106124226047.0 | F79: 精装 | G79: 48.73 | H79: 120 | I79: 4 | J79: =MEDIAN(租金配对!K228:K231) -> 0.019168684 | K79: https://cd.lianjia.com/ershoufang/106124226047.html | L79: =MEDIAN(租金配对!L228:L231) -> 0.021666667
A80: 合江亭 | B80: 喜年广场 | C80: 40–60㎡ | D80: 1室1厅 | E80: 106124518344.0 | F80: 精装 | G80: 46.89 | H80: 106 | I80: 4 | J80: =MEDIAN(租金配对!K256:K259) -> 0.021940244 | K80: https://cd.lianjia.com/ershoufang/106124518344.html | L80: =MEDIAN(租金配对!L256:L259) -> 0.024528302
A81: 合江亭 | B81: 喜年广场 | C81: 40–60㎡ | D81: 1室1厅 | E81: 106124598987.0 | F81: 精装 | G81: 46.89 | H81: 98 | I81: 4 | J81: =MEDIAN(租金配对!K248:K251) -> 0.023879528 | K81: https://cd.lianjia.com/ershoufang/106124598987.html | L81: =MEDIAN(租金配对!L248:L251) -> 0.026530612
A82: 合江亭 | B82: 喜年广场 | C82: 40–60㎡ | D82: 1室1厅 | E82: 106124700408.0 | F82: 精装 | G82: 46.77 | H82: 104 | I82: 4 | J82: =MEDIAN(租金配对!K216:K219) -> 0.022397094 | K82: https://cd.lianjia.com/ershoufang/106124700408.html | L82: =MEDIAN(租金配对!L216:L219) -> 0.025
A83: 合江亭 | B83: 喜年广场 | C83: 40–60㎡ | D83: 1室1厅 | E83: 106125735818.0 | F83: 精装 | G83: 46.77 | H83: 105 | I83: 4 | J83: =MEDIAN(租金配对!K232:K235) -> 0.022166494 | K83: https://cd.lianjia.com/ershoufang/106125735818.html | L83: =MEDIAN(租金配对!L232:L235) -> 0.024761905
A84: 合江亭 | B84: 喜年广场 | C84: 40–60㎡ | D84: 1室1厅 | E84: 106127193850.0 | F84: 精装 | G84: 47.06 | H84: 115 | I84: 4 | J84: =MEDIAN(租金配对!K240:K243) -> 0.020081061 | K84: https://cd.lianjia.com/ershoufang/106127193850.html | L84: =MEDIAN(租金配对!L240:L243) -> 0.022608696
A85: 合江亭 | B85: 喜年广场 | C85: 40–60㎡ | D85: 1室1厅 | E85: 106127476091.0 | F85: 精装 | G85: 46.89 | H85: 115 | I85: 4 | J85: =MEDIAN(租金配对!K236:K239) -> 0.020081061 | K85: https://cd.lianjia.com/ershoufang/106127476091.html | L85: =MEDIAN(租金配对!L236:L239) -> 0.022608696
A86: 合江亭 | B86: 喜年广场 | C86: 40–60㎡ | D86: 1室1厅 | E86: 106128196190.0 | F86: 精装 | G86: 46.81 | H86: 105 | I86: 4 | J86: =MEDIAN(租金配对!K224:K227) -> 0.022166494 | K86: https://cd.lianjia.com/ershoufang/106128196190.html | L86: =MEDIAN(租金配对!L224:L227) -> 0.024761905
A87: 合江亭 | B87: 喜年广场 | C87: 40–60㎡ | D87: 1室1厅 | E87: 106128416793.0 | F87: 精装 | G87: 46.89 | H87: 98 | I87: 4 | J87: =MEDIAN(租金配对!K220:K223) -> 0.023879528 | K87: https://cd.lianjia.com/ershoufang/106128416793.html | L87: =MEDIAN(租金配对!L220:L223) -> 0.026530612
A88: 合江亭 | B88: 喜年广场 | C88: 40–60㎡ | D88: 1室1厅 | E88: 106129651912.0 | F88: 精装 | G88: 46.89 | H88: 88 | I88: 4 | J88: =MEDIAN(租金配对!K212:K215) -> 0.026799472 | K88: https://cd.lianjia.com/ershoufang/106129651912.html | L88: =MEDIAN(租金配对!L212:L215) -> 0.029545455
A89: 合江亭 | B89: 喜年广场 | C89: 40–60㎡ | D89: 1室1厅 | E89: 106129659913.0 | F89: 精装 | G89: 46.78 | H89: 99 | I89: 4 | J89: =MEDIAN(租金配对!K244:K247) -> 0.023619977 | K89: https://cd.lianjia.com/ershoufang/106129659913.html | L89: =MEDIAN(租金配对!L244:L247) -> 0.026262626
A90: 合江亭 | B90: 喜年广场 | C90: 40–60㎡ | D90: 1室1厅 | E90: 106129739034.0 | F90: 精装 | G90: 46.89 | H90: 88 | I90: 4 | J90: =MEDIAN(租金配对!K252:K255) -> 0.026799472 | K90: https://cd.lianjia.com/ershoufang/106129739034.html | L90: =MEDIAN(租金配对!L252:L255) -> 0.029545455
A91: 合江亭 | B91: 国际商务大厦 | C91: 40–60㎡ | D91: 1室0厅 | E91: nan | F91: 精装 | G91: 44.54 | H91: 110 | I91: 4 | J91: =MEDIAN(租金配对!K260:K263) -> 0.015793529 | K91: https://cd.lianjia.com/ershoufang/106125090492.html | L91: =MEDIAN(租金配对!L260:L263) -> 0.018181818
A92: 合江亭 | B92: 国际商务大厦 | C92: 40–60㎡ | D92: 1室1厅 | E92: 106125252557.0 | F92: 精装 | G92: 56.15 | H92: 108 | I92: 0 | K92: https://cd.lianjia.com/ershoufang/106125252557.html
A93: 合江亭 | B93: 国际商务大厦 | C93: 40–60㎡ | D93: 1室1厅 | E93: 106125252645.0 | F93: 精装 | G93: 58.54 | H93: 109 | I93: 0 | K93: https://cd.lianjia.com/ershoufang/106125252645.html
A94: 合江亭 | B94: 国际商务大厦 | C94: 40–60㎡ | D94: 1室1厅 | E94: 106127954865.0 | F94: 简装 | G94: 42.94 | H94: 103 | I94: 1 | J94: =MEDIAN(租金配对!K266:K266) -> 0.016990291 | K94: https://cd.lianjia.com/ershoufang/106127954865.html | L94: =MEDIAN(租金配对!L266:L266) -> 0.019417476
A95: 合江亭 | B95: 国际商务大厦 | C95: 40–60㎡ | D95: 1室1厅 | E95: 106127954891.0 | F95: 简装 | G95: 42.94 | H95: 103 | I95: 1 | J95: =MEDIAN(租金配对!K265:K265) -> 0.016990291 | K95: https://cd.lianjia.com/ershoufang/106127954891.html | L95: =MEDIAN(租金配对!L265:L265) -> 0.019417476
A96: 合江亭 | B96: 国际商务大厦 | C96: 40–60㎡ | D96: 1室1厅 | E96: 106128517937.0 | F96: 简装 | G96: 44.54 | H96: 88.8 | I96: 1 | J96: =MEDIAN(租金配对!K264:K264) -> 0.019997601 | K96: https://cd.lianjia.com/ershoufang/106128517937.html | L96: =MEDIAN(租金配对!L264:L264) -> 0.022522523
A97: 合江亭 | B97: 国际商务大厦 | C97: 40–60㎡ | D97: 1室1厅 | E97: 106128532608.0 | F97: 精装 | G97: 45.71 | H97: 108 | I97: 1 | J97: =MEDIAN(租金配对!K267:K267) -> 0.016119631 | K97: https://cd.lianjia.com/ershoufang/106128532608.html | L97: =MEDIAN(租金配对!L267:L267) -> 0.018518519
A98: 合江亭 | B98: 总府花园 | C98: 60–90㎡ | D98: 1室2厅 | E98: 106128098689.0 | F98: 精装 | G98: 87.32 | H98: 115 | I98: 0 | K98: https://cd.lianjia.com/ershoufang/106128098689.html
A99: 合江亭 | B99: 总府花园 | C99: 60–90㎡ | D99: 2室1厅 | E99: 106124507363.0 | F99: 简装 | G99: 68.75 | H99: 102 | I99: 3 | J99: =MEDIAN(租金配对!K271:K273) -> 0.022871861 | K99: https://cd.lianjia.com/ershoufang/106124507363.html | L99: =MEDIAN(租金配对!L271:L273) -> 0.025490196
A100: 合江亭 | B100: 总府花园 | C100: 60–90㎡ | D100: 2室1厅 | E100: 106129096024.0 | F100: 简装 | G100: 68.75 | H100: 118 | I100: 3 | J100: =MEDIAN(租金配对!K268:K270) -> 0.019524357 | K100: https://cd.lianjia.com/ershoufang/106129096024.html | L100: =MEDIAN(租金配对!L268:L270) -> 0.022033898
A101: 合江亭 | B101: 总府花园 | C101: 60–90㎡ | D101: 2室2厅 | E101: 106128825041.0 | F101: 简装 | G101: 83.51 | H101: 115 | I101: 2 | J101: =MEDIAN(租金配对!K274:K275) -> 0.034819455 | K101: https://cd.lianjia.com/ershoufang/106128825041.html | L101: =MEDIAN(租金配对!L274:L275) -> 0.037826087
A102: 合江亭 | B102: 星城银座 | C102: 40–60㎡ | D102: 1室0厅 | E102: 106128494446.0 | F102: 精装 | G102: 46.8 | H102: 118 | I102: 1 | J102: =MEDIAN(租金配对!K280:K280) -> 0.012958099 | K102: https://cd.lianjia.com/ershoufang/106128494446.html | L102: =MEDIAN(租金配对!L280:L280) -> 0.015254237
A103: 合江亭 | B103: 星城银座 | C103: 40–60㎡ | D103: 1室0厅 | E103: 106128890609.0 | F103: 精装 | G103: 50.61 | H103: 88 | I103: 1 | J103: =MEDIAN(租金配对!K279:K279) -> 0.017994717 | K103: https://cd.lianjia.com/ershoufang/106128890609.html | L103: =MEDIAN(租金配对!L279:L279) -> 0.020454545
...

Sheet 租金配对
A2: 2587个出售-出租配对
A3: 逐对扣买入成本及卖出摊销；各出售房源的多个配对仅用于求其自身中位数
A6: 商圈 | B6: 小区 | C6: 面积段 | D6: 房型 | E6: 出售编号 | F6: 出租编号 | G6: 出售面积㎡ | H6: 出租面积㎡ | I6: 售价万 | J6: 租金元/月 | K6: 调整后回报率 | L6: 原毛回报率 | M6: 卖出月摊销元
A7: 华西 | B7: 丽景天成 | C7: 40–60㎡ | D7: 1室1厅 | E7: 106129483566.0 | F7: CD2190079646437998592 | G7: 59.3 | H7: 57.93 | I7: 97 | J7: 2200 | K7: =(J7-M7)*税费参数!$B$12/(I7*10000*(1+SUM(税费参数!$B$6:$B$8))) -> 0.02015052 | L7: =J7*税费参数!$B$12/(I7*10000) -> 0.022680412 | M7: =I7*10000*SUM(税费参数!$B$9:$B$10)/税费参数!$B$11 -> 181.875
A8: 华西 | B8: 丽景天成 | C8: 40–60㎡ | D8: 1室1厅 | E8: 106129483566.0 | F8: CD2202410575210741760 | G8: 59.3 | H8: 60 | I8: 97 | J8: 2300 | K8: =(J8-M8)*税费参数!$B$12/(I8*10000*(1+SUM(税费参数!$B$6:$B$8))) -> 0.021148998 | L8: =J8*税费参数!$B$12/(I8*10000) -> 0.02371134 | M8: =I8*10000*SUM(税费参数!$B$9:$B$10)/税费参数!$B$11 -> 181.875
A9: 华西 | B9: 丽景天成 | C9: 40–60㎡ | D9: 1室1厅 | E9: 106129412042.0 | F9: CD2190079646437998592 | G9: 57.93 | H9: 57.93 | I9: 95 | J9: 2200 | K9: =(J9-M9)*税费参数!$B$12/(I9*10000*(1+SUM(税费参数!$B$6:$B$8))) -> 0.020612973 | L9: =J9*税费参数!$B$12/(I9*10000) -> 0.023157895 | M9: =I9*10000*SUM(税费参数!$B$9:$B$10)/税费参数!$B$11 -> 178.125
A10: 华西 | B10: 丽景天成 | C10: 40–60㎡ | D10: 1室1厅 | E10: 106129412042.0 | F10: CD2202410575210741760 | G10: 57.93 | H10: 60 | I10: 95 | J10: 2300 | K10: =(J10-M10)*税费参数!$B$12/(I10*10000*(1+SUM(税费参数!$B$6:$B$8))) -> 0.021632471 | L10: =J10*税费参数!$B$12/(I10*10000) -> 0.024210526 | M10: =I10*10000*SUM(税费参数!$B$9:$B$10)/税费参数!$B$11 -> 178.125
A11: 华西 | B11: 丽景天成 | C11: 60–90㎡ | D11: 1室1厅 | E11: 106117140666.0 | F11: CD2195559948966952960 | G11: 60.74 | H11: 62.16 | I11: 110 | J11: 2400 | K11: =(J11-M11)*税费参数!$B$12/(I11*10000*(1+SUM(税费参数!$B$6:$B$8))) -> 0.01931543 | L11: =J11*税费参数!$B$12/(I11*10000) -> 0.021818182 | M11: =I11*10000*SUM(税费参数!$B$9:$B$10)/税费参数!$B$11 -> 206.25
A12: 华西 | B12: 丽景天成 | C12: 60–90㎡ | D12: 1室1厅 | E12: 106114386047.0 | F12: CD2195559948966952960 | G12: 60.74 | H12: 62.16 | I12: 120 | J12: 2400 | K12: =(J12-M12)*税费参数!$B$12/(I12*10000*(1+SUM(税费参数!$B$6:$B$8))) -> 0.017554479 | L12: =J12*税费参数!$B$12/(I12*10000) -> 0.02 | M12: =I12*10000*SUM(税费参数!$B$9:$B$10)/税费参数!$B$11 -> 225
A13: 华西 | B13: 傲仕门 | C13: 40–60㎡ | D13: 1室1厅 | E13: 106121807884.0 | F13: CD2201683724582518784 | G13: 55.41 | H13: 59.44 | I13: 95 | J13: 2700 | K13: =(J13-M13)*税费参数!$B$12/(I13*10000*(1+SUM(税费参数!$B$6:$B$8))) -> 0.025710463 | L13: =J13*税费参数!$B$12/(I13*10000) -> 0.028421053 | M13: =I13*10000*SUM(税费参数!$B$9:$B$10)/税费参数!$B$11 -> 178.125
A14: 华西 | B14: 傲仕门 | C14: 40–60㎡ | D14: 1室1厅 | E14: 106121807884.0 | F14: CD2214344428011651072 | G14: 55.41 | H14: 57.05 | I14: 95 | J14: 2300 | K14: =(J14-M14)*税费参数!$B$12/(I14*10000*(1+SUM(税费参数!$B$6:$B$8))) -> 0.021632471 | L14: =J14*税费参数!$B$12/(I14*10000) -> 0.024210526 | M14: =I14*10000*SUM(税费参数!$B$9:$B$10)/税费参数!$B$11 -> 178.125
A15: 华西 | B15: 傲仕门 | C15: 40–60㎡ | D15: 1室1厅 | E15: 106123379786.0 | F15: CD2201683724582518784 | G15: 59.44 | H15: 59.44 | I15: 95 | J15: 2700 | K15: =(J15-M15)*税费参数!$B$12/(I15*10000*(1+SUM(税费参数!$B$6:$B$8))) -> 0.025710463 | L15: =J15*税费参数!$B$12/(I15*10000) -> 0.028421053 | M15: =I15*10000*SUM(税费参数!$B$9:$B$10)/税费参数!$B$11 -> 178.125
A16: 华西 | B16: 傲仕门 | C16: 40–60㎡ | D16: 1室1厅 | E16: 106123379786.0 | F16: CD2214344428011651072 | G16: 59.44 | H16: 57.05 | I16: 95 | J16: 2300 | K16: =(J16-M16)*税费参数!$B$12/(I16*10000*(1+SUM(税费参数!$B$6:$B$8))) -> 0.021632471 | L16: =J16*税费参数!$B$12/(I16*10000) -> 0.024210526 | M16: =I16*10000*SUM(税费参数!$B$9:$B$10)/税费参数!$B$11 -> 178.125
A17: 华西 | B17: 凯蒂阳光 | C17: 40–60㎡ | D17: 1室1厅 | E17: 106123405462.0 | F17: CD2218601000455897088 | G17: 51.94 | H17: 48.56 | I17: 98 | J17: 2600 | K17: =(J17-M17)*税费参数!$B$12/(I17*10000*(1+SUM(税费参数!$B$6:$B$8))) -> 0.023879528 | L17: =J17*税费参数!$B$12/(I17*10000) -> 0.026530612 | M17: =I17*10000*SUM(税费参数!$B$9:$B$10)/税费参数!$B$11 -> 183.75
A18: 华西 | B18: 凯蒂阳光 | C18: 40–60㎡ | D18: 1室1厅 | E18: 106123405462.0 | F18: CD2197054279691272192 | G18: 51.94 | H18: 48.56 | I18: 98 | J18: 2800 | K18: =(J18-M18)*税费参数!$B$12/(I18*10000*(1+SUM(税费参数!$B$6:$B$8))) -> 0.025856105 | L18: =J18*税费参数!$B$12/(I18*10000) -> 0.028571429 | M18: =I18*10000*SUM(税费参数!$B$9:$B$10)/税费参数!$B$11 -> 183.75
... A2593: 西南财大 | B2593: 金沙时代城 | C2593: 40–60㎡ | D2593: 1室0厅 | E2593: 106126871807.0 | F2593: CD1998980433844371456 | G2593: 46.5 | H2593: 46.5 | I2593: 35 | J2593: 1800 | K2593: =(J2593-M2593)*税费参数!$B$12/(I2593*10000*(1+SUM(税费参数!$B$6:$B$8))) -> 0.047993774 | L2593: =J2593*税费参数!$B$12/(I2593*10000) -> 0.051428571 | M2593: =I2593*10000*SUM(税费参数!$B$9:$B$10)/税费参数!$B$11 -> 65.625
